{
  "a_comp_cor_00": {
    "CumulativeVarianceExplained": 0.016882941,
    "Mask": "combined",
    "Method": "aCompCor",
    "Retained": true,
    "SingularValue": 81.5424888363,
    "VarianceExplained": 0.016882941
  },
  "a_comp_cor_01": {
    "CumulativeVarianceExplained": 0.0304727266,
    "Mask": "combined",
    "Method": "aCompCor",
    "Retained": true,
    "SingularValue": 73.1587394385,
    "VarianceExplained": 0.0135897856
  },
  "a_comp_cor_02": {
    "CumulativeVarianceExplained": 0.0438562234,
    "Mask": "combined",
    "Method": "aCompCor",
    "Retained": true,
    "SingularValue": 72.6013525019,
    "VarianceExplained": 0.0133834968
  },
  "a_comp_cor_03": {
    "CumulativeVarianceExplained": 0.0556607085,
    "Mask": "combined",
    "Method": "aCompCor",
    "Retained": true,
    "SingularValue": 68.1841506602,
    "VarianceExplained": 0.0118044851
  },
  "a_comp_cor_04": {
    "CumulativeVarianceExplained": 0.0669263148,
    "Mask": "combined",
    "Method": "aCompCor",
    "Retained": true,
    "SingularValue": 66.6096570486,
    "VarianceExplained": 0.0112656064
  },
  "a_comp_cor_05": {
    "CumulativeVarianceExplained": 0.0771488644,
    "Mask": "combined",
    "Method": "aCompCor",
    "Retained": true,
    "SingularValue": 63.4511536207,
    "VarianceExplained": 0.0102225495
  },
  "a_comp_cor_06": {
    "CumulativeVarianceExplained": 0.0856082743,
    "Mask": "combined",
    "Method": "aCompCor",
    "Retained": true,
    "SingularValue": 57.720481925,
    "VarianceExplained": 0.00845941
  },
  "a_comp_cor_07": {
    "CumulativeVarianceExplained": 0.0938524951,
    "Mask": "combined",
    "Method": "aCompCor",
    "Retained": true,
    "SingularValue": 56.9816102176,
    "VarianceExplained": 0.0082442208
  },
  "a_comp_cor_08": {
    "CumulativeVarianceExplained": 0.1019456802,
    "Mask": "combined",
    "Method": "aCompCor",
    "Retained": true,
    "SingularValue": 56.4572405671,
    "VarianceExplained": 0.0080931851
  },
  "a_comp_cor_09": {
    "CumulativeVarianceExplained": 0.1097698553,
    "Mask": "combined",
    "Method": "aCompCor",
    "Retained": true,
    "SingularValue": 55.511018112,
    "VarianceExplained": 0.0078241751
  },
  "a_comp_cor_10": {
    "CumulativeVarianceExplained": 0.1174738704,
    "Mask": "combined",
    "Method": "aCompCor",
    "Retained": true,
    "SingularValue": 55.0831128029,
    "VarianceExplained": 0.0077040151
  },
  "a_comp_cor_11": {
    "CumulativeVarianceExplained": 0.1251074832,
    "Mask": "combined",
    "Method": "aCompCor",
    "Retained": true,
    "SingularValue": 54.830849494,
    "VarianceExplained": 0.0076336128
  },
  "a_comp_cor_12": {
    "CumulativeVarianceExplained": 0.1325551278,
    "Mask": "combined",
    "Method": "aCompCor",
    "Retained": true,
    "SingularValue": 54.1588437761,
    "VarianceExplained": 0.0074476446
  },
  "a_comp_cor_13": {
    "CumulativeVarianceExplained": 0.1399507289,
    "Mask": "combined",
    "Method": "aCompCor",
    "Retained": true,
    "SingularValue": 53.9692832009,
    "VarianceExplained": 0.0073956011
  },
  "a_comp_cor_14": {
    "CumulativeVarianceExplained": 0.1472699783,
    "Mask": "combined",
    "Method": "aCompCor",
    "Retained": true,
    "SingularValue": 53.6899727608,
    "VarianceExplained": 0.0073192494
  },
  "a_comp_cor_15": {
    "CumulativeVarianceExplained": 0.1545045359,
    "Mask": "combined",
    "Method": "aCompCor",
    "Retained": true,
    "SingularValue": 53.3784428832,
    "VarianceExplained": 0.0072345576
  },
  "a_comp_cor_16": {
    "CumulativeVarianceExplained": 0.1617241352,
    "Mask": "combined",
    "Method": "aCompCor",
    "Retained": true,
    "SingularValue": 53.3232312087,
    "VarianceExplained": 0.0072195993
  },
  "a_comp_cor_17": {
    "CumulativeVarianceExplained": 0.1688259264,
    "Mask": "combined",
    "Method": "aCompCor",
    "Retained": true,
    "SingularValue": 52.8863825549,
    "VarianceExplained": 0.0071017912
  },
  "a_comp_cor_18": {
    "CumulativeVarianceExplained": 0.1758278945,
    "Mask": "combined",
    "Method": "aCompCor",
    "Retained": true,
    "SingularValue": 52.5133801718,
    "VarianceExplained": 0.0070019681
  },
  "a_comp_cor_19": {
    "CumulativeVarianceExplained": 0.1827974678,
    "Mask": "combined",
    "Method": "aCompCor",
    "Retained": true,
    "SingularValue": 52.3917622938,
    "VarianceExplained": 0.0069695733
  },
  "a_comp_cor_20": {
    "CumulativeVarianceExplained": 0.1896942485,
    "Mask": "combined",
    "Method": "aCompCor",
    "Retained": true,
    "SingularValue": 52.1174453865,
    "VarianceExplained": 0.0068967807
  },
  "a_comp_cor_21": {
    "CumulativeVarianceExplained": 0.196540219,
    "Mask": "combined",
    "Method": "aCompCor",
    "Retained": true,
    "SingularValue": 51.9251095579,
    "VarianceExplained": 0.0068459705
  },
  "a_comp_cor_22": {
    "CumulativeVarianceExplained": 0.2033376132,
    "Mask": "combined",
    "Method": "aCompCor",
    "Retained": true,
    "SingularValue": 51.7405620929,
    "VarianceExplained": 0.0067973943
  },
  "a_comp_cor_23": {
    "CumulativeVarianceExplained": 0.2100718722,
    "Mask": "combined",
    "Method": "aCompCor",
    "Retained": true,
    "SingularValue": 51.4997141046,
    "VarianceExplained": 0.006734259
  },
  "a_comp_cor_24": {
    "CumulativeVarianceExplained": 0.2166803889,
    "Mask": "combined",
    "Method": "aCompCor",
    "Retained": true,
    "SingularValue": 51.0166463602,
    "VarianceExplained": 0.0066085167
  },
  "a_comp_cor_25": {
    "CumulativeVarianceExplained": 0.223270552,
    "Mask": "combined",
    "Method": "aCompCor",
    "Retained": true,
    "SingularValue": 50.945753737,
    "VarianceExplained": 0.0065901631
  },
  "a_comp_cor_26": {
    "CumulativeVarianceExplained": 0.2298355217,
    "Mask": "combined",
    "Method": "aCompCor",
    "Retained": true,
    "SingularValue": 50.8482811488,
    "VarianceExplained": 0.0065649698
  },
  "a_comp_cor_27": {
    "CumulativeVarianceExplained": 0.2363900162,
    "Mask": "combined",
    "Method": "aCompCor",
    "Retained": true,
    "SingularValue": 50.8076971082,
    "VarianceExplained": 0.0065544944
  },
  "a_comp_cor_28": {
    "CumulativeVarianceExplained": 0.2428280148,
    "Mask": "combined",
    "Method": "aCompCor",
    "Retained": true,
    "SingularValue": 50.3541597666,
    "VarianceExplained": 0.0064379987
  },
  "a_comp_cor_29": {
    "CumulativeVarianceExplained": 0.2492614016,
    "Mask": "combined",
    "Method": "aCompCor",
    "Retained": true,
    "SingularValue": 50.3361205905,
    "VarianceExplained": 0.0064333867
  },
  "a_comp_cor_30": {
    "CumulativeVarianceExplained": 0.2556365636,
    "Mask": "combined",
    "Method": "aCompCor",
    "Retained": true,
    "SingularValue": 50.1078217948,
    "VarianceExplained": 0.006375162
  },
  "a_comp_cor_31": {
    "CumulativeVarianceExplained": 0.2619743499,
    "Mask": "combined",
    "Method": "aCompCor",
    "Retained": true,
    "SingularValue": 49.9607221988,
    "VarianceExplained": 0.0063377863
  },
  "a_comp_cor_32": {
    "CumulativeVarianceExplained": 0.2682612736,
    "Mask": "combined",
    "Method": "aCompCor",
    "Retained": true,
    "SingularValue": 49.7598433652,
    "VarianceExplained": 0.0062869237
  },
  "a_comp_cor_33": {
    "CumulativeVarianceExplained": 0.2744881496,
    "Mask": "combined",
    "Method": "aCompCor",
    "Retained": true,
    "SingularValue": 49.5216403919,
    "VarianceExplained": 0.0062268761
  },
  "a_comp_cor_34": {
    "CumulativeVarianceExplained": 0.2806675748,
    "Mask": "combined",
    "Method": "aCompCor",
    "Retained": true,
    "SingularValue": 49.3325937257,
    "VarianceExplained": 0.0061794252
  },
  "a_comp_cor_35": {
    "CumulativeVarianceExplained": 0.2868094856,
    "Mask": "combined",
    "Method": "aCompCor",
    "Retained": true,
    "SingularValue": 49.1826205336,
    "VarianceExplained": 0.0061419108
  },
  "a_comp_cor_36": {
    "CumulativeVarianceExplained": 0.2929118144,
    "Mask": "combined",
    "Method": "aCompCor",
    "Retained": true,
    "SingularValue": 49.0238836721,
    "VarianceExplained": 0.0061023288
  },
  "a_comp_cor_37": {
    "CumulativeVarianceExplained": 0.2989937572,
    "Mask": "combined",
    "Method": "aCompCor",
    "Retained": true,
    "SingularValue": 48.9419283677,
    "VarianceExplained": 0.0060819428
  },
  "a_comp_cor_38": {
    "CumulativeVarianceExplained": 0.3050659932,
    "Mask": "combined",
    "Method": "aCompCor",
    "Retained": true,
    "SingularValue": 48.9028568882,
    "VarianceExplained": 0.006072236
  },
  "a_comp_cor_39": {
    "CumulativeVarianceExplained": 0.3110903142,
    "Mask": "combined",
    "Method": "aCompCor",
    "Retained": true,
    "SingularValue": 48.7095328351,
    "VarianceExplained": 0.006024321
  },
  "a_comp_cor_40": {
    "CumulativeVarianceExplained": 0.3170700858,
    "Mask": "combined",
    "Method": "aCompCor",
    "Retained": true,
    "SingularValue": 48.5290970566,
    "VarianceExplained": 0.0059797716
  },
  "a_comp_cor_41": {
    "CumulativeVarianceExplained": 0.3230196314,
    "Mask": "combined",
    "Method": "aCompCor",
    "Retained": true,
    "SingularValue": 48.4062910489,
    "VarianceExplained": 0.0059495455
  },
  "a_comp_cor_42": {
    "CumulativeVarianceExplained": 0.3289377992,
    "Mask": "combined",
    "Method": "aCompCor",
    "Retained": true,
    "SingularValue": 48.278475598,
    "VarianceExplained": 0.0059181678
  },
  "a_comp_cor_43": {
    "CumulativeVarianceExplained": 0.3347789616,
    "Mask": "combined",
    "Method": "aCompCor",
    "Retained": true,
    "SingularValue": 47.9633547868,
    "VarianceExplained": 0.0058411624
  },
  "a_comp_cor_44": {
    "CumulativeVarianceExplained": 0.340607065,
    "Mask": "combined",
    "Method": "aCompCor",
    "Retained": true,
    "SingularValue": 47.9097092434,
    "VarianceExplained": 0.0058281034
  },
  "a_comp_cor_45": {
    "CumulativeVarianceExplained": 0.3464134066,
    "Mask": "combined",
    "Method": "aCompCor",
    "Retained": true,
    "SingularValue": 47.8201798004,
    "VarianceExplained": 0.0058063417
  },
  "a_comp_cor_46": {
    "CumulativeVarianceExplained": 0.3521917456,
    "Mask": "combined",
    "Method": "aCompCor",
    "Retained": true,
    "SingularValue": 47.7047275262,
    "VarianceExplained": 0.005778339
  },
  "a_comp_cor_47": {
    "CumulativeVarianceExplained": 0.3579321372,
    "Mask": "combined",
    "Method": "aCompCor",
    "Retained": true,
    "SingularValue": 47.5478266377,
    "VarianceExplained": 0.0057403916
  },
  "a_comp_cor_48": {
    "CumulativeVarianceExplained": 0.3636524766,
    "Mask": "combined",
    "Method": "aCompCor",
    "Retained": true,
    "SingularValue": 47.4647075398,
    "VarianceExplained": 0.0057203394
  },
  "a_comp_cor_49": {
    "CumulativeVarianceExplained": 0.3693585397,
    "Mask": "combined",
    "Method": "aCompCor",
    "Retained": true,
    "SingularValue": 47.4054416358,
    "VarianceExplained": 0.0057060631
  },
  "a_comp_cor_50": {
    "CumulativeVarianceExplained": 0.375014689,
    "Mask": "combined",
    "Method": "aCompCor",
    "Retained": true,
    "SingularValue": 47.1976464925,
    "VarianceExplained": 0.0056561493
  },
  "a_comp_cor_51": {
    "CumulativeVarianceExplained": 0.380649436,
    "Mask": "combined",
    "Method": "aCompCor",
    "Retained": true,
    "SingularValue": 47.1082665753,
    "VarianceExplained": 0.0056347471
  },
  "a_comp_cor_52": {
    "CumulativeVarianceExplained": 0.3862422166,
    "Mask": "combined",
    "Method": "aCompCor",
    "Retained": true,
    "SingularValue": 46.9325121646,
    "VarianceExplained": 0.0055927806
  },
  "a_comp_cor_53": {
    "CumulativeVarianceExplained": 0.3918011645,
    "Mask": "combined",
    "Method": "aCompCor",
    "Retained": true,
    "SingularValue": 46.7903414342,
    "VarianceExplained": 0.0055589479
  },
  "a_comp_cor_54": {
    "CumulativeVarianceExplained": 0.3973483082,
    "Mask": "combined",
    "Method": "aCompCor",
    "Retained": true,
    "SingularValue": 46.740636165,
    "VarianceExplained": 0.0055471437
  },
  "a_comp_cor_55": {
    "CumulativeVarianceExplained": 0.4028581775,
    "Mask": "combined",
    "Method": "aCompCor",
    "Retained": true,
    "SingularValue": 46.5833329755,
    "VarianceExplained": 0.0055098693
  },
  "a_comp_cor_56": {
    "CumulativeVarianceExplained": 0.4083272634,
    "Mask": "combined",
    "Method": "aCompCor",
    "Retained": true,
    "SingularValue": 46.4106108973,
    "VarianceExplained": 0.0054690859
  },
  "a_comp_cor_57": {
    "CumulativeVarianceExplained": 0.413766839,
    "Mask": "combined",
    "Method": "aCompCor",
    "Retained": true,
    "SingularValue": 46.2852292006,
    "VarianceExplained": 0.0054395756
  },
  "a_comp_cor_58": {
    "CumulativeVarianceExplained": 0.4191722117,
    "Mask": "combined",
    "Method": "aCompCor",
    "Retained": true,
    "SingularValue": 46.1394843859,
    "VarianceExplained": 0.0054053728
  },
  "a_comp_cor_59": {
    "CumulativeVarianceExplained": 0.4245339076,
    "Mask": "combined",
    "Method": "aCompCor",
    "Retained": true,
    "SingularValue": 45.9526963273,
    "VarianceExplained": 0.0053616959
  },
  "a_comp_cor_60": {
    "CumulativeVarianceExplained": 0.4298630337,
    "Mask": "combined",
    "Method": "aCompCor",
    "Retained": true,
    "SingularValue": 45.8129130845,
    "VarianceExplained": 0.0053291261
  },
  "a_comp_cor_61": {
    "CumulativeVarianceExplained": 0.435165132,
    "Mask": "combined",
    "Method": "aCompCor",
    "Retained": true,
    "SingularValue": 45.6965907678,
    "VarianceExplained": 0.0053020983
  },
  "a_comp_cor_62": {
    "CumulativeVarianceExplained": 0.4404518737,
    "Mask": "combined",
    "Method": "aCompCor",
    "Retained": true,
    "SingularValue": 45.6303665841,
    "VarianceExplained": 0.0052867417
  },
  "a_comp_cor_63": {
    "CumulativeVarianceExplained": 0.4457050208,
    "Mask": "combined",
    "Method": "aCompCor",
    "Retained": true,
    "SingularValue": 45.4851564265,
    "VarianceExplained": 0.0052531471
  },
  "a_comp_cor_64": {
    "CumulativeVarianceExplained": 0.4509027394,
    "Mask": "combined",
    "Method": "aCompCor",
    "Retained": true,
    "SingularValue": 45.2445518353,
    "VarianceExplained": 0.0051977185
  },
  "a_comp_cor_65": {
    "CumulativeVarianceExplained": 0.4560709823,
    "Mask": "combined",
    "Method": "aCompCor",
    "Retained": true,
    "SingularValue": 45.1160813879,
    "VarianceExplained": 0.0051682429
  },
  "a_comp_cor_66": {
    "CumulativeVarianceExplained": 0.4612125798,
    "Mask": "combined",
    "Method": "aCompCor",
    "Retained": true,
    "SingularValue": 44.9996307304,
    "VarianceExplained": 0.0051415975
  },
  "a_comp_cor_67": {
    "CumulativeVarianceExplained": 0.4663366545,
    "Mask": "combined",
    "Method": "aCompCor",
    "Retained": true,
    "SingularValue": 44.9228849245,
    "VarianceExplained": 0.0051240747
  },
  "a_comp_cor_68": {
    "CumulativeVarianceExplained": 0.4714034503,
    "Mask": "combined",
    "Method": "aCompCor",
    "Retained": true,
    "SingularValue": 44.671096225,
    "VarianceExplained": 0.0050667957
  },
  "a_comp_cor_69": {
    "CumulativeVarianceExplained": 0.4764419372,
    "Mask": "combined",
    "Method": "aCompCor",
    "Retained": true,
    "SingularValue": 44.5461300174,
    "VarianceExplained": 0.0050384869
  },
  "a_comp_cor_70": {
    "CumulativeVarianceExplained": 0.4814595826,
    "Mask": "combined",
    "Method": "aCompCor",
    "Retained": true,
    "SingularValue": 44.4539026402,
    "VarianceExplained": 0.0050176454
  },
  "a_comp_cor_71": {
    "CumulativeVarianceExplained": 0.4864645059,
    "Mask": "combined",
    "Method": "aCompCor",
    "Retained": true,
    "SingularValue": 44.3975111282,
    "VarianceExplained": 0.0050049233
  },
  "a_comp_cor_72": {
    "CumulativeVarianceExplained": 0.4914210961,
    "Mask": "combined",
    "Method": "aCompCor",
    "Retained": true,
    "SingularValue": 44.1826151007,
    "VarianceExplained": 0.0049565902
  },
  "a_comp_cor_73": {
    "CumulativeVarianceExplained": 0.4963516862,
    "Mask": "combined",
    "Method": "aCompCor",
    "Retained": true,
    "SingularValue": 44.0665815591,
    "VarianceExplained": 0.0049305901
  },
  "a_comp_cor_74": {
    "CumulativeVarianceExplained": 0.5012653735,
    "Mask": "combined",
    "Method": "aCompCor",
    "Retained": true,
    "SingularValue": 43.9909831936,
    "VarianceExplained": 0.0049136873
  },
  "c_comp_cor_00": {
    "CumulativeVarianceExplained": 0.082343209,
    "Mask": "CSF",
    "Method": "aCompCor",
    "Retained": true,
    "SingularValue": 74.3872545912,
    "VarianceExplained": 0.082343209
  },
  "c_comp_cor_01": {
    "CumulativeVarianceExplained": 0.1442780168,
    "Mask": "CSF",
    "Method": "aCompCor",
    "Retained": true,
    "SingularValue": 64.5137123459,
    "VarianceExplained": 0.0619348077
  },
  "c_comp_cor_02": {
    "CumulativeVarianceExplained": 0.2030789082,
    "Mask": "CSF",
    "Method": "aCompCor",
    "Retained": true,
    "SingularValue": 62.860320574,
    "VarianceExplained": 0.0588008914
  },
  "c_comp_cor_03": {
    "CumulativeVarianceExplained": 0.2561106319,
    "Mask": "CSF",
    "Method": "aCompCor",
    "Retained": true,
    "SingularValue": 59.6970001913,
    "VarianceExplained": 0.0530317237
  },
  "c_comp_cor_04": {
    "CumulativeVarianceExplained": 0.2969884301,
    "Mask": "CSF",
    "Method": "aCompCor",
    "Retained": true,
    "SingularValue": 52.4117166607,
    "VarianceExplained": 0.0408777983
  },
  "c_comp_cor_05": {
    "CumulativeVarianceExplained": 0.3324091245,
    "Mask": "CSF",
    "Method": "aCompCor",
    "Retained": true,
    "SingularValue": 48.788017615,
    "VarianceExplained": 0.0354206944
  },
  "c_comp_cor_06": {
    "CumulativeVarianceExplained": 0.3633279905,
    "Mask": "CSF",
    "Method": "aCompCor",
    "Retained": true,
    "SingularValue": 45.5823188654,
    "VarianceExplained": 0.030918866
  },
  "c_comp_cor_07": {
    "CumulativeVarianceExplained": 0.3875662724,
    "Mask": "CSF",
    "Method": "aCompCor",
    "Retained": true,
    "SingularValue": 40.3585498536,
    "VarianceExplained": 0.0242382819
  },
  "c_comp_cor_08": {
    "CumulativeVarianceExplained": 0.4085533129,
    "Mask": "CSF",
    "Method": "aCompCor",
    "Retained": true,
    "SingularValue": 37.5543489189,
    "VarianceExplained": 0.0209870405
  },
  "c_comp_cor_09": {
    "CumulativeVarianceExplained": 0.4292097219,
    "Mask": "CSF",
    "Method": "aCompCor",
    "Retained": true,
    "SingularValue": 37.2573573985,
    "VarianceExplained": 0.0206564089
  },
  "c_comp_cor_10": {
    "CumulativeVarianceExplained": 0.4457799508,
    "Mask": "CSF",
    "Method": "aCompCor",
    "Retained": true,
    "SingularValue": 33.3694378833,
    "VarianceExplained": 0.0165702289
  },
  "c_comp_cor_11": {
    "CumulativeVarianceExplained": 0.4599578091,
    "Mask": "CSF",
    "Method": "aCompCor",
    "Retained": true,
    "SingularValue": 30.8666822832,
    "VarianceExplained": 0.0141778583
  },
  "c_comp_cor_12": {
    "CumulativeVarianceExplained": 0.4731559252,
    "Mask": "CSF",
    "Method": "aCompCor",
    "Retained": true,
    "SingularValue": 29.7810913863,
    "VarianceExplained": 0.0131981161
  },
  "c_comp_cor_13": {
    "CumulativeVarianceExplained": 0.4852729366,
    "Mask": "CSF",
    "Method": "aCompCor",
    "Retained": true,
    "SingularValue": 28.5352968872,
    "VarianceExplained": 0.0121170114
  },
  "c_comp_cor_14": {
    "CumulativeVarianceExplained": 0.4969560633,
    "Mask": "CSF",
    "Method": "aCompCor",
    "Retained": true,
    "SingularValue": 28.0197450237,
    "VarianceExplained": 0.0116831267
  },
  "c_comp_cor_15": {
    "CumulativeVarianceExplained": 0.5083574851,
    "Mask": "CSF",
    "Method": "aCompCor",
    "Retained": true,
    "SingularValue": 27.6798762087,
    "VarianceExplained": 0.0114014218
  },
  "dropped_0": {
    "CumulativeVarianceExplained": 0.2735798576,
    "Mask": "Edge",
    "Method": "EdgeRegressor",
    "Retained": false,
    "SingularValue": 118.2270695412,
    "VarianceExplained": 0.0049884511
  },
  "dropped_1": {
    "CumulativeVarianceExplained": 0.2785346835,
    "Mask": "Edge",
    "Method": "EdgeRegressor",
    "Retained": false,
    "SingularValue": 117.8279344911,
    "VarianceExplained": 0.0049548259
  },
  "dropped_10": {
    "CumulativeVarianceExplained": 0.320963131,
    "Mask": "Edge",
    "Method": "EdgeRegressor",
    "Retained": false,
    "SingularValue": 113.2644079651,
    "VarianceExplained": 0.0045784533
  },
  "dropped_100": {
    "CumulativeVarianceExplained": 0.6729194117,
    "Mask": "Edge",
    "Method": "EdgeRegressor",
    "Retained": false,
    "SingularValue": 98.6904187964,
    "VarianceExplained": 0.0034760167
  },
  "dropped_101": {
    "CumulativeVarianceExplained": 0.6763876059,
    "Mask": "Edge",
    "Method": "EdgeRegressor",
    "Retained": false,
    "SingularValue": 98.5793094449,
    "VarianceExplained": 0.0034681942
  },
  "dropped_102": {
    "CumulativeVarianceExplained": 0.6798464915,
    "Mask": "Edge",
    "Method": "EdgeRegressor",
    "Retained": false,
    "SingularValue": 98.4469266006,
    "VarianceExplained": 0.0034588856
  },
  "dropped_103": {
    "CumulativeVarianceExplained": 0.6832997195,
    "Mask": "Edge",
    "Method": "EdgeRegressor",
    "Retained": false,
    "SingularValue": 98.3663802913,
    "VarianceExplained": 0.003453228
  },
  "dropped_104": {
    "CumulativeVarianceExplained": 0.6867403297,
    "Mask": "Edge",
    "Method": "EdgeRegressor",
    "Retained": false,
    "SingularValue": 98.186504959,
    "VarianceExplained": 0.0034406102
  },
  "dropped_105": {
    "CumulativeVarianceExplained": 0.6901680868,
    "Mask": "Edge",
    "Method": "EdgeRegressor",
    "Retained": false,
    "SingularValue": 98.0029359508,
    "VarianceExplained": 0.0034277571
  },
  "dropped_106": {
    "CumulativeVarianceExplained": 0.6935897082,
    "Mask": "Edge",
    "Method": "EdgeRegressor",
    "Retained": false,
    "SingularValue": 97.9151839598,
    "VarianceExplained": 0.0034216214
  },
  "dropped_107": {
    "CumulativeVarianceExplained": 0.69700513,
    "Mask": "Edge",
    "Method": "EdgeRegressor",
    "Retained": false,
    "SingularValue": 97.8264372611,
    "VarianceExplained": 0.0034154218
  },
  "dropped_108": {
    "CumulativeVarianceExplained": 0.700419351,
    "Mask": "Edge",
    "Method": "EdgeRegressor",
    "Retained": false,
    "SingularValue": 97.8092387977,
    "VarianceExplained": 0.003414221
  },
  "dropped_109": {
    "CumulativeVarianceExplained": 0.7038208073,
    "Mask": "Edge",
    "Method": "EdgeRegressor",
    "Retained": false,
    "SingularValue": 97.6262284094,
    "VarianceExplained": 0.0034014563
  },
  "dropped_11": {
    "CumulativeVarianceExplained": 0.3254927376,
    "Mask": "Edge",
    "Method": "EdgeRegressor",
    "Retained": false,
    "SingularValue": 112.6585887313,
    "VarianceExplained": 0.0045296066
  },
  "dropped_110": {
    "CumulativeVarianceExplained": 0.7072149308,
    "Mask": "Edge",
    "Method": "EdgeRegressor",
    "Retained": false,
    "SingularValue": 97.5209421,
    "VarianceExplained": 0.0033941235
  },
  "dropped_111": {
    "CumulativeVarianceExplained": 0.7106069653,
    "Mask": "Edge",
    "Method": "EdgeRegressor",
    "Retained": false,
    "SingularValue": 97.4909262377,
    "VarianceExplained": 0.0033920345
  },
  "dropped_112": {
    "CumulativeVarianceExplained": 0.7139822371,
    "Mask": "Edge",
    "Method": "EdgeRegressor",
    "Retained": false,
    "SingularValue": 97.249737671,
    "VarianceExplained": 0.0033752718
  },
  "dropped_113": {
    "CumulativeVarianceExplained": 0.7173506896,
    "Mask": "Edge",
    "Method": "EdgeRegressor",
    "Retained": false,
    "SingularValue": 97.1514481984,
    "VarianceExplained": 0.0033684525
  },
  "dropped_114": {
    "CumulativeVarianceExplained": 0.7207088221,
    "Mask": "Edge",
    "Method": "EdgeRegressor",
    "Retained": false,
    "SingularValue": 97.0025119318,
    "VarianceExplained": 0.0033581325
  },
  "dropped_115": {
    "CumulativeVarianceExplained": 0.7240587107,
    "Mask": "Edge",
    "Method": "EdgeRegressor",
    "Retained": false,
    "SingularValue": 96.8833731909,
    "VarianceExplained": 0.0033498887
  },
  "dropped_116": {
    "CumulativeVarianceExplained": 0.7274025459,
    "Mask": "Edge",
    "Method": "EdgeRegressor",
    "Retained": false,
    "SingularValue": 96.7957953576,
    "VarianceExplained": 0.0033438351
  },
  "dropped_117": {
    "CumulativeVarianceExplained": 0.7307456154,
    "Mask": "Edge",
    "Method": "EdgeRegressor",
    "Retained": false,
    "SingularValue": 96.7847136309,
    "VarianceExplained": 0.0033430695
  },
  "dropped_118": {
    "CumulativeVarianceExplained": 0.7340775422,
    "Mask": "Edge",
    "Method": "EdgeRegressor",
    "Retained": false,
    "SingularValue": 96.6232833536,
    "VarianceExplained": 0.0033319268
  },
  "dropped_119": {
    "CumulativeVarianceExplained": 0.737397413,
    "Mask": "Edge",
    "Method": "EdgeRegressor",
    "Retained": false,
    "SingularValue": 96.4483183382,
    "VarianceExplained": 0.0033198708
  },
  "dropped_12": {
    "CumulativeVarianceExplained": 0.3299915078,
    "Mask": "Edge",
    "Method": "EdgeRegressor",
    "Retained": false,
    "SingularValue": 112.274458078,
    "VarianceExplained": 0.0044987701
  },
  "dropped_120": {
    "CumulativeVarianceExplained": 0.7407094785,
    "Mask": "Edge",
    "Method": "EdgeRegressor",
    "Retained": false,
    "SingularValue": 96.3348718676,
    "VarianceExplained": 0.0033120655
  },
  "dropped_121": {
    "CumulativeVarianceExplained": 0.7440175296,
    "Mask": "Edge",
    "Method": "EdgeRegressor",
    "Retained": false,
    "SingularValue": 96.2764728827,
    "VarianceExplained": 0.0033080511
  },
  "dropped_122": {
    "CumulativeVarianceExplained": 0.7473224332,
    "Mask": "Edge",
    "Method": "EdgeRegressor",
    "Retained": false,
    "SingularValue": 96.2306596001,
    "VarianceExplained": 0.0033049036
  },
  "dropped_123": {
    "CumulativeVarianceExplained": 0.7506150538,
    "Mask": "Edge",
    "Method": "EdgeRegressor",
    "Retained": false,
    "SingularValue": 96.0516680924,
    "VarianceExplained": 0.0032926206
  },
  "dropped_124": {
    "CumulativeVarianceExplained": 0.7539025219,
    "Mask": "Edge",
    "Method": "EdgeRegressor",
    "Retained": false,
    "SingularValue": 95.9764839485,
    "VarianceExplained": 0.003287468
  },
  "dropped_125": {
    "CumulativeVarianceExplained": 0.7571785419,
    "Mask": "Edge",
    "Method": "EdgeRegressor",
    "Retained": false,
    "SingularValue": 95.809227012,
    "VarianceExplained": 0.00327602
  },
  "dropped_126": {
    "CumulativeVarianceExplained": 0.7604492018,
    "Mask": "Edge",
    "Method": "EdgeRegressor",
    "Retained": false,
    "SingularValue": 95.7308159502,
    "VarianceExplained": 0.0032706599
  },
  "dropped_127": {
    "CumulativeVarianceExplained": 0.7637125875,
    "Mask": "Edge",
    "Method": "EdgeRegressor",
    "Retained": false,
    "SingularValue": 95.6243008114,
    "VarianceExplained": 0.0032633858
  },
  "dropped_128": {
    "CumulativeVarianceExplained": 0.766966303,
    "Mask": "Edge",
    "Method": "EdgeRegressor",
    "Retained": false,
    "SingularValue": 95.4825158837,
    "VarianceExplained": 0.0032537155
  },
  "dropped_129": {
    "CumulativeVarianceExplained": 0.770215398,
    "Mask": "Edge",
    "Method": "EdgeRegressor",
    "Retained": false,
    "SingularValue": 95.4146951304,
    "VarianceExplained": 0.0032490949
  },
  "dropped_13": {
    "CumulativeVarianceExplained": 0.3344663657,
    "Mask": "Edge",
    "Method": "EdgeRegressor",
    "Retained": false,
    "SingularValue": 111.9756759465,
    "VarianceExplained": 0.004474858
  },
  "dropped_130": {
    "CumulativeVarianceExplained": 0.7734548864,
    "Mask": "Edge",
    "Method": "EdgeRegressor",
    "Retained": false,
    "SingularValue": 95.273535128,
    "VarianceExplained": 0.0032394884
  },
  "dropped_131": {
    "CumulativeVarianceExplained": 0.7766843483,
    "Mask": "Edge",
    "Method": "EdgeRegressor",
    "Retained": false,
    "SingularValue": 95.1259811659,
    "VarianceExplained": 0.0032294619
  },
  "dropped_132": {
    "CumulativeVarianceExplained": 0.77990769,
    "Mask": "Edge",
    "Method": "EdgeRegressor",
    "Retained": false,
    "SingularValue": 95.0358007712,
    "VarianceExplained": 0.0032233417
  },
  "dropped_133": {
    "CumulativeVarianceExplained": 0.7831255333,
    "Mask": "Edge",
    "Method": "EdgeRegressor",
    "Retained": false,
    "SingularValue": 94.9547103693,
    "VarianceExplained": 0.0032178433
  },
  "dropped_134": {
    "CumulativeVarianceExplained": 0.7863286355,
    "Mask": "Edge",
    "Method": "EdgeRegressor",
    "Retained": false,
    "SingularValue": 94.7369630426,
    "VarianceExplained": 0.0032031021
  },
  "dropped_135": {
    "CumulativeVarianceExplained": 0.7895243534,
    "Mask": "Edge",
    "Method": "EdgeRegressor",
    "Retained": false,
    "SingularValue": 94.6276998109,
    "VarianceExplained": 0.0031957179
  },
  "dropped_136": {
    "CumulativeVarianceExplained": 0.7927147898,
    "Mask": "Edge",
    "Method": "EdgeRegressor",
    "Retained": false,
    "SingularValue": 94.5494725258,
    "VarianceExplained": 0.0031904364
  },
  "dropped_137": {
    "CumulativeVarianceExplained": 0.7959008628,
    "Mask": "Edge",
    "Method": "EdgeRegressor",
    "Retained": false,
    "SingularValue": 94.4847963598,
    "VarianceExplained": 0.0031860731
  },
  "dropped_138": {
    "CumulativeVarianceExplained": 0.7990831948,
    "Mask": "Edge",
    "Method": "EdgeRegressor",
    "Retained": false,
    "SingularValue": 94.4293073574,
    "VarianceExplained": 0.0031823319
  },
  "dropped_139": {
    "CumulativeVarianceExplained": 0.8022520154,
    "Mask": "Edge",
    "Method": "EdgeRegressor",
    "Retained": false,
    "SingularValue": 94.2286335708,
    "VarianceExplained": 0.0031688206
  },
  "dropped_14": {
    "CumulativeVarianceExplained": 0.3389274461,
    "Mask": "Edge",
    "Method": "EdgeRegressor",
    "Retained": false,
    "SingularValue": 111.803163383,
    "VarianceExplained": 0.0044610804
  },
  "dropped_140": {
    "CumulativeVarianceExplained": 0.8054150349,
    "Mask": "Edge",
    "Method": "EdgeRegressor",
    "Retained": false,
    "SingularValue": 94.1423419443,
    "VarianceExplained": 0.0031630195
  },
  "dropped_141": {
    "CumulativeVarianceExplained": 0.808568632,
    "Mask": "Edge",
    "Method": "EdgeRegressor",
    "Retained": false,
    "SingularValue": 94.0020171728,
    "VarianceExplained": 0.0031535972
  },
  "dropped_142": {
    "CumulativeVarianceExplained": 0.8117124415,
    "Mask": "Edge",
    "Method": "EdgeRegressor",
    "Retained": false,
    "SingularValue": 93.8560283093,
    "VarianceExplained": 0.0031438094
  },
  "dropped_143": {
    "CumulativeVarianceExplained": 0.8148490029,
    "Mask": "Edge",
    "Method": "EdgeRegressor",
    "Retained": false,
    "SingularValue": 93.7477738291,
    "VarianceExplained": 0.0031365614
  },
  "dropped_144": {
    "CumulativeVarianceExplained": 0.8179744601,
    "Mask": "Edge",
    "Method": "EdgeRegressor",
    "Retained": false,
    "SingularValue": 93.5816812502,
    "VarianceExplained": 0.0031254572
  },
  "dropped_145": {
    "CumulativeVarianceExplained": 0.8210912096,
    "Mask": "Edge",
    "Method": "EdgeRegressor",
    "Retained": false,
    "SingularValue": 93.4512284142,
    "VarianceExplained": 0.0031167495
  },
  "dropped_146": {
    "CumulativeVarianceExplained": 0.8242013627,
    "Mask": "Edge",
    "Method": "EdgeRegressor",
    "Retained": false,
    "SingularValue": 93.3522854256,
    "VarianceExplained": 0.0031101532
  },
  "dropped_147": {
    "CumulativeVarianceExplained": 0.8273098195,
    "Mask": "Edge",
    "Method": "EdgeRegressor",
    "Retained": false,
    "SingularValue": 93.3268229978,
    "VarianceExplained": 0.0031084568
  },
  "dropped_148": {
    "CumulativeVarianceExplained": 0.8304129184,
    "Mask": "Edge",
    "Method": "EdgeRegressor",
    "Retained": false,
    "SingularValue": 93.2463564051,
    "VarianceExplained": 0.0031030989
  },
  "dropped_149": {
    "CumulativeVarianceExplained": 0.8335055485,
    "Mask": "Edge",
    "Method": "EdgeRegressor",
    "Retained": false,
    "SingularValue": 93.0889340995,
    "VarianceExplained": 0.0030926301
  },
  "dropped_15": {
    "CumulativeVarianceExplained": 0.3433744603,
    "Mask": "Edge",
    "Method": "EdgeRegressor",
    "Retained": false,
    "SingularValue": 111.626760933,
    "VarianceExplained": 0.0044470142
  },
  "dropped_150": {
    "CumulativeVarianceExplained": 0.8365930925,
    "Mask": "Edge",
    "Method": "EdgeRegressor",
    "Retained": false,
    "SingularValue": 93.0123552713,
    "VarianceExplained": 0.003087544
  },
  "dropped_151": {
    "CumulativeVarianceExplained": 0.8396699806,
    "Mask": "Edge",
    "Method": "EdgeRegressor",
    "Retained": false,
    "SingularValue": 92.851711585,
    "VarianceExplained": 0.0030768881
  },
  "dropped_152": {
    "CumulativeVarianceExplained": 0.8427434115,
    "Mask": "Edge",
    "Method": "EdgeRegressor",
    "Retained": false,
    "SingularValue": 92.7995339432,
    "VarianceExplained": 0.0030734309
  },
  "dropped_153": {
    "CumulativeVarianceExplained": 0.8458020771,
    "Mask": "Edge",
    "Method": "EdgeRegressor",
    "Retained": false,
    "SingularValue": 92.5763521897,
    "VarianceExplained": 0.0030586656
  },
  "dropped_154": {
    "CumulativeVarianceExplained": 0.8488531779,
    "Mask": "Edge",
    "Method": "EdgeRegressor",
    "Retained": false,
    "SingularValue": 92.4617996213,
    "VarianceExplained": 0.0030511008
  },
  "dropped_155": {
    "CumulativeVarianceExplained": 0.8519013478,
    "Mask": "Edge",
    "Method": "EdgeRegressor",
    "Retained": false,
    "SingularValue": 92.4173797589,
    "VarianceExplained": 0.0030481699
  },
  "dropped_156": {
    "CumulativeVarianceExplained": 0.8549367383,
    "Mask": "Edge",
    "Method": "EdgeRegressor",
    "Retained": false,
    "SingularValue": 92.2234473642,
    "VarianceExplained": 0.0030353905
  },
  "dropped_157": {
    "CumulativeVarianceExplained": 0.8579603267,
    "Mask": "Edge",
    "Method": "EdgeRegressor",
    "Retained": false,
    "SingularValue": 92.0439827714,
    "VarianceExplained": 0.0030235884
  },
  "dropped_158": {
    "CumulativeVarianceExplained": 0.8609746478,
    "Mask": "Edge",
    "Method": "EdgeRegressor",
    "Retained": false,
    "SingularValue": 91.9028160563,
    "VarianceExplained": 0.0030143211
  },
  "dropped_159": {
    "CumulativeVarianceExplained": 0.8639745912,
    "Mask": "Edge",
    "Method": "EdgeRegressor",
    "Retained": false,
    "SingularValue": 91.6833759752,
    "VarianceExplained": 0.0029999434
  },
  "dropped_16": {
    "CumulativeVarianceExplained": 0.347795429,
    "Mask": "Edge",
    "Method": "EdgeRegressor",
    "Retained": false,
    "SingularValue": 111.2993904628,
    "VarianceExplained": 0.0044209687
  },
  "dropped_160": {
    "CumulativeVarianceExplained": 0.8669718144,
    "Mask": "Edge",
    "Method": "EdgeRegressor",
    "Retained": false,
    "SingularValue": 91.6417997684,
    "VarianceExplained": 0.0029972232
  },
  "dropped_161": {
    "CumulativeVarianceExplained": 0.8699664221,
    "Mask": "Edge",
    "Method": "EdgeRegressor",
    "Retained": false,
    "SingularValue": 91.6018055969,
    "VarianceExplained": 0.0029946077
  },
  "dropped_162": {
    "CumulativeVarianceExplained": 0.872947342,
    "Mask": "Edge",
    "Method": "EdgeRegressor",
    "Retained": false,
    "SingularValue": 91.3922182278,
    "VarianceExplained": 0.0029809199
  },
  "dropped_163": {
    "CumulativeVarianceExplained": 0.8759208057,
    "Mask": "Edge",
    "Method": "EdgeRegressor",
    "Retained": false,
    "SingularValue": 91.2778467694,
    "VarianceExplained": 0.0029734637
  },
  "dropped_164": {
    "CumulativeVarianceExplained": 0.8788896523,
    "Mask": "Edge",
    "Method": "EdgeRegressor",
    "Retained": false,
    "SingularValue": 91.2069525034,
    "VarianceExplained": 0.0029688466
  },
  "dropped_165": {
    "CumulativeVarianceExplained": 0.881851359,
    "Mask": "Edge",
    "Method": "EdgeRegressor",
    "Retained": false,
    "SingularValue": 91.0972131362,
    "VarianceExplained": 0.0029617067
  },
  "dropped_166": {
    "CumulativeVarianceExplained": 0.8848099326,
    "Mask": "Edge",
    "Method": "EdgeRegressor",
    "Retained": false,
    "SingularValue": 91.0490149238,
    "VarianceExplained": 0.0029585736
  },
  "dropped_167": {
    "CumulativeVarianceExplained": 0.8877547115,
    "Mask": "Edge",
    "Method": "EdgeRegressor",
    "Retained": false,
    "SingularValue": 90.8365034301,
    "VarianceExplained": 0.0029447789
  },
  "dropped_168": {
    "CumulativeVarianceExplained": 0.8906949939,
    "Mask": "Edge",
    "Method": "EdgeRegressor",
    "Retained": false,
    "SingularValue": 90.7671272862,
    "VarianceExplained": 0.0029402824
  },
  "dropped_169": {
    "CumulativeVarianceExplained": 0.8936236941,
    "Mask": "Edge",
    "Method": "EdgeRegressor",
    "Retained": false,
    "SingularValue": 90.5881776887,
    "VarianceExplained": 0.0029287002
  },
  "dropped_17": {
    "CumulativeVarianceExplained": 0.352193558,
    "Mask": "Edge",
    "Method": "EdgeRegressor",
    "Retained": false,
    "SingularValue": 111.0115188525,
    "VarianceExplained": 0.004398129
  },
  "dropped_170": {
    "CumulativeVarianceExplained": 0.8965483606,
    "Mask": "Edge",
    "Method": "EdgeRegressor",
    "Retained": false,
    "SingularValue": 90.5257720537,
    "VarianceExplained": 0.0029246665
  },
  "dropped_171": {
    "CumulativeVarianceExplained": 0.8994703174,
    "Mask": "Edge",
    "Method": "EdgeRegressor",
    "Retained": false,
    "SingularValue": 90.4838274933,
    "VarianceExplained": 0.0029219568
  },
  "dropped_172": {
    "CumulativeVarianceExplained": 0.9023831487,
    "Mask": "Edge",
    "Method": "EdgeRegressor",
    "Retained": false,
    "SingularValue": 90.3424229362,
    "VarianceExplained": 0.0029128313
  },
  "dropped_173": {
    "CumulativeVarianceExplained": 0.9052835598,
    "Mask": "Edge",
    "Method": "EdgeRegressor",
    "Retained": false,
    "SingularValue": 90.149607631,
    "VarianceExplained": 0.002900411
  },
  "dropped_174": {
    "CumulativeVarianceExplained": 0.9081776989,
    "Mask": "Edge",
    "Method": "EdgeRegressor",
    "Retained": false,
    "SingularValue": 90.0520845026,
    "VarianceExplained": 0.0028941392
  },
  "dropped_175": {
    "CumulativeVarianceExplained": 0.9110612129,
    "Mask": "Edge",
    "Method": "EdgeRegressor",
    "Retained": false,
    "SingularValue": 89.8866302181,
    "VarianceExplained": 0.002883514
  },
  "dropped_176": {
    "CumulativeVarianceExplained": 0.9139391772,
    "Mask": "Edge",
    "Method": "EdgeRegressor",
    "Retained": false,
    "SingularValue": 89.8000883755,
    "VarianceExplained": 0.0028779643
  },
  "dropped_177": {
    "CumulativeVarianceExplained": 0.9168073148,
    "Mask": "Edge",
    "Method": "EdgeRegressor",
    "Retained": false,
    "SingularValue": 89.646648297,
    "VarianceExplained": 0.0028681376
  },
  "dropped_178": {
    "CumulativeVarianceExplained": 0.9196566496,
    "Mask": "Edge",
    "Method": "EdgeRegressor",
    "Retained": false,
    "SingularValue": 89.3523150867,
    "VarianceExplained": 0.0028493348
  },
  "dropped_179": {
    "CumulativeVarianceExplained": 0.9225019342,
    "Mask": "Edge",
    "Method": "EdgeRegressor",
    "Retained": false,
    "SingularValue": 89.2887861508,
    "VarianceExplained": 0.0028452846
  },
  "dropped_18": {
    "CumulativeVarianceExplained": 0.3565723588,
    "Mask": "Edge",
    "Method": "EdgeRegressor",
    "Retained": false,
    "SingularValue": 110.7673228765,
    "VarianceExplained": 0.0043788008
  },
  "dropped_180": {
    "CumulativeVarianceExplained": 0.9253468669,
    "Mask": "Edge",
    "Method": "EdgeRegressor",
    "Retained": false,
    "SingularValue": 89.283264735,
    "VarianceExplained": 0.0028449327
  },
  "dropped_181": {
    "CumulativeVarianceExplained": 0.9281799521,
    "Mask": "Edge",
    "Method": "EdgeRegressor",
    "Retained": false,
    "SingularValue": 89.097164989,
    "VarianceExplained": 0.0028330852
  },
  "dropped_182": {
    "CumulativeVarianceExplained": 0.9310060663,
    "Mask": "Edge",
    "Method": "EdgeRegressor",
    "Retained": false,
    "SingularValue": 88.9874825856,
    "VarianceExplained": 0.0028261142
  },
  "dropped_183": {
    "CumulativeVarianceExplained": 0.9338202456,
    "Mask": "Edge",
    "Method": "EdgeRegressor",
    "Retained": false,
    "SingularValue": 88.799383102,
    "VarianceExplained": 0.0028141793
  },
  "dropped_184": {
    "CumulativeVarianceExplained": 0.936630991,
    "Mask": "Edge",
    "Method": "EdgeRegressor",
    "Retained": false,
    "SingularValue": 88.7451881571,
    "VarianceExplained": 0.0028107453
  },
  "dropped_185": {
    "CumulativeVarianceExplained": 0.9394298853,
    "Mask": "Edge",
    "Method": "EdgeRegressor",
    "Retained": false,
    "SingularValue": 88.557901546,
    "VarianceExplained": 0.0027988943
  },
  "dropped_186": {
    "CumulativeVarianceExplained": 0.9422196205,
    "Mask": "Edge",
    "Method": "EdgeRegressor",
    "Retained": false,
    "SingularValue": 88.4128842391,
    "VarianceExplained": 0.0027897352
  },
  "dropped_187": {
    "CumulativeVarianceExplained": 0.9450020009,
    "Mask": "Edge",
    "Method": "EdgeRegressor",
    "Retained": false,
    "SingularValue": 88.2962622199,
    "VarianceExplained": 0.0027823804
  },
  "dropped_188": {
    "CumulativeVarianceExplained": 0.9477706412,
    "Mask": "Edge",
    "Method": "EdgeRegressor",
    "Retained": false,
    "SingularValue": 88.0779768078,
    "VarianceExplained": 0.0027686403
  },
  "dropped_189": {
    "CumulativeVarianceExplained": 0.9505346738,
    "Mask": "Edge",
    "Method": "EdgeRegressor",
    "Retained": false,
    "SingularValue": 88.0046546157,
    "VarianceExplained": 0.0027640326
  },
  "dropped_19": {
    "CumulativeVarianceExplained": 0.3609224967,
    "Mask": "Edge",
    "Method": "EdgeRegressor",
    "Retained": false,
    "SingularValue": 110.4041955621,
    "VarianceExplained": 0.0043501379
  },
  "dropped_190": {
    "CumulativeVarianceExplained": 0.9532764121,
    "Mask": "Edge",
    "Method": "EdgeRegressor",
    "Retained": false,
    "SingularValue": 87.6490209565,
    "VarianceExplained": 0.0027417384
  },
  "dropped_191": {
    "CumulativeVarianceExplained": 0.9560139761,
    "Mask": "Edge",
    "Method": "EdgeRegressor",
    "Retained": false,
    "SingularValue": 87.5822713878,
    "VarianceExplained": 0.002737564
  },
  "dropped_192": {
    "CumulativeVarianceExplained": 0.9587509827,
    "Mask": "Edge",
    "Method": "EdgeRegressor",
    "Retained": false,
    "SingularValue": 87.5733557368,
    "VarianceExplained": 0.0027370067
  },
  "dropped_193": {
    "CumulativeVarianceExplained": 0.9614688519,
    "Mask": "Edge",
    "Method": "EdgeRegressor",
    "Retained": false,
    "SingularValue": 87.2666573172,
    "VarianceExplained": 0.0027178692
  },
  "dropped_194": {
    "CumulativeVarianceExplained": 0.9641773168,
    "Mask": "Edge",
    "Method": "EdgeRegressor",
    "Retained": false,
    "SingularValue": 87.1155477432,
    "VarianceExplained": 0.0027084649
  },
  "dropped_195": {
    "CumulativeVarianceExplained": 0.9668778533,
    "Mask": "Edge",
    "Method": "EdgeRegressor",
    "Retained": false,
    "SingularValue": 86.9879476291,
    "VarianceExplained": 0.0027005364
  },
  "dropped_196": {
    "CumulativeVarianceExplained": 0.9695745396,
    "Mask": "Edge",
    "Method": "EdgeRegressor",
    "Retained": false,
    "SingularValue": 86.9259171654,
    "VarianceExplained": 0.0026966863
  },
  "dropped_197": {
    "CumulativeVarianceExplained": 0.9722562995,
    "Mask": "Edge",
    "Method": "EdgeRegressor",
    "Retained": false,
    "SingularValue": 86.6850116308,
    "VarianceExplained": 0.0026817599
  },
  "dropped_198": {
    "CumulativeVarianceExplained": 0.9749348873,
    "Mask": "Edge",
    "Method": "EdgeRegressor",
    "Retained": false,
    "SingularValue": 86.6337289556,
    "VarianceExplained": 0.0026785878
  },
  "dropped_199": {
    "CumulativeVarianceExplained": 0.9776033942,
    "Mask": "Edge",
    "Method": "EdgeRegressor",
    "Retained": false,
    "SingularValue": 86.4705522784,
    "VarianceExplained": 0.0026685069
  },
  "dropped_2": {
    "CumulativeVarianceExplained": 0.2834191581,
    "Mask": "Edge",
    "Method": "EdgeRegressor",
    "Retained": false,
    "SingularValue": 116.9884518264,
    "VarianceExplained": 0.0048844746
  },
  "dropped_20": {
    "CumulativeVarianceExplained": 0.3652515648,
    "Mask": "Edge",
    "Method": "EdgeRegressor",
    "Retained": false,
    "SingularValue": 110.1365009737,
    "VarianceExplained": 0.0043290681
  },
  "dropped_200": {
    "CumulativeVarianceExplained": 0.9802618675,
    "Mask": "Edge",
    "Method": "EdgeRegressor",
    "Retained": false,
    "SingularValue": 86.30783411,
    "VarianceExplained": 0.0026584733
  },
  "dropped_201": {
    "CumulativeVarianceExplained": 0.9828976685,
    "Mask": "Edge",
    "Method": "EdgeRegressor",
    "Retained": false,
    "SingularValue": 85.9390152625,
    "VarianceExplained": 0.002635801
  },
  "dropped_202": {
    "CumulativeVarianceExplained": 0.9855093986,
    "Mask": "Edge",
    "Method": "EdgeRegressor",
    "Retained": false,
    "SingularValue": 85.5457054971,
    "VarianceExplained": 0.0026117301
  },
  "dropped_203": {
    "CumulativeVarianceExplained": 0.988111944,
    "Mask": "Edge",
    "Method": "EdgeRegressor",
    "Retained": false,
    "SingularValue": 85.3951528104,
    "VarianceExplained": 0.0026025454
  },
  "dropped_204": {
    "CumulativeVarianceExplained": 0.9907020248,
    "Mask": "Edge",
    "Method": "EdgeRegressor",
    "Retained": false,
    "SingularValue": 85.190413573,
    "VarianceExplained": 0.0025900809
  },
  "dropped_205": {
    "CumulativeVarianceExplained": 0.993270333,
    "Mask": "Edge",
    "Method": "EdgeRegressor",
    "Retained": false,
    "SingularValue": 84.831595339,
    "VarianceExplained": 0.0025683082
  },
  "dropped_206": {
    "CumulativeVarianceExplained": 0.9958204242,
    "Mask": "Edge",
    "Method": "EdgeRegressor",
    "Retained": false,
    "SingularValue": 84.5302038888,
    "VarianceExplained": 0.0025500911
  },
  "dropped_207": {
    "CumulativeVarianceExplained": 0.9981492146,
    "Mask": "Edge",
    "Method": "EdgeRegressor",
    "Retained": false,
    "SingularValue": 80.7791487372,
    "VarianceExplained": 0.0023287905
  },
  "dropped_208": {
    "CumulativeVarianceExplained": 1.0,
    "Mask": "Edge",
    "Method": "EdgeRegressor",
    "Retained": false,
    "SingularValue": 72.0131977373,
    "VarianceExplained": 0.0018507854
  },
  "dropped_209": {
    "CumulativeVarianceExplained": 1.0,
    "Mask": "Edge",
    "Method": "EdgeRegressor",
    "Retained": false,
    "SingularValue": 0.0,
    "VarianceExplained": 0.0
  },
  "dropped_21": {
    "CumulativeVarianceExplained": 0.3695644694,
    "Mask": "Edge",
    "Method": "EdgeRegressor",
    "Retained": false,
    "SingularValue": 109.9306997594,
    "VarianceExplained": 0.0043129046
  },
  "dropped_210": {
    "CumulativeVarianceExplained": 1.0,
    "Mask": "Edge",
    "Method": "EdgeRegressor",
    "Retained": false,
    "SingularValue": 0.0,
    "VarianceExplained": 0.0
  },
  "dropped_211": {
    "CumulativeVarianceExplained": 1.0,
    "Mask": "Edge",
    "Method": "EdgeRegressor",
    "Retained": false,
    "SingularValue": 0.0,
    "VarianceExplained": 0.0
  },
  "dropped_212": {
    "CumulativeVarianceExplained": 1.0,
    "Mask": "Edge",
    "Method": "EdgeRegressor",
    "Retained": false,
    "SingularValue": 0.0,
    "VarianceExplained": 0.0
  },
  "dropped_213": {
    "CumulativeVarianceExplained": 1.0,
    "Mask": "Edge",
    "Method": "EdgeRegressor",
    "Retained": false,
    "SingularValue": 0.0,
    "VarianceExplained": 0.0
  },
  "dropped_214": {
    "CumulativeVarianceExplained": 1.0,
    "Mask": "Edge",
    "Method": "EdgeRegressor",
    "Retained": false,
    "SingularValue": 0.0,
    "VarianceExplained": 0.0
  },
  "dropped_215": {
    "CumulativeVarianceExplained": 1.0,
    "Mask": "Edge",
    "Method": "EdgeRegressor",
    "Retained": false,
    "SingularValue": 0.0,
    "VarianceExplained": 0.0
  },
  "dropped_22": {
    "CumulativeVarianceExplained": 0.3738648012,
    "Mask": "Edge",
    "Method": "EdgeRegressor",
    "Retained": false,
    "SingularValue": 109.7703500573,
    "VarianceExplained": 0.0043003318
  },
  "dropped_23": {
    "CumulativeVarianceExplained": 0.3781451033,
    "Mask": "Edge",
    "Method": "EdgeRegressor",
    "Retained": false,
    "SingularValue": 109.5144116832,
    "VarianceExplained": 0.0042803021
  },
  "dropped_24": {
    "CumulativeVarianceExplained": 0.3824212441,
    "Mask": "Edge",
    "Method": "EdgeRegressor",
    "Retained": false,
    "SingularValue": 109.4611649683,
    "VarianceExplained": 0.0042761408
  },
  "dropped_25": {
    "CumulativeVarianceExplained": 0.3866792734,
    "Mask": "Edge",
    "Method": "EdgeRegressor",
    "Retained": false,
    "SingularValue": 109.2291084253,
    "VarianceExplained": 0.0042580293
  },
  "dropped_26": {
    "CumulativeVarianceExplained": 0.3909241289,
    "Mask": "Edge",
    "Method": "EdgeRegressor",
    "Retained": false,
    "SingularValue": 109.060006973,
    "VarianceExplained": 0.0042448555
  },
  "dropped_27": {
    "CumulativeVarianceExplained": 0.3951394685,
    "Mask": "Edge",
    "Method": "EdgeRegressor",
    "Retained": false,
    "SingularValue": 108.6801802025,
    "VarianceExplained": 0.0042153396
  },
  "dropped_28": {
    "CumulativeVarianceExplained": 0.3993473138,
    "Mask": "Edge",
    "Method": "EdgeRegressor",
    "Retained": false,
    "SingularValue": 108.5835269286,
    "VarianceExplained": 0.0042078452
  },
  "dropped_29": {
    "CumulativeVarianceExplained": 0.4035388136,
    "Mask": "Edge",
    "Method": "EdgeRegressor",
    "Retained": false,
    "SingularValue": 108.3724251388,
    "VarianceExplained": 0.0041914998
  },
  "dropped_3": {
    "CumulativeVarianceExplained": 0.2882568745,
    "Mask": "Edge",
    "Method": "EdgeRegressor",
    "Retained": false,
    "SingularValue": 116.4271502958,
    "VarianceExplained": 0.0048377164
  },
  "dropped_30": {
    "CumulativeVarianceExplained": 0.4077099311,
    "Mask": "Edge",
    "Method": "EdgeRegressor",
    "Retained": false,
    "SingularValue": 108.1086080694,
    "VarianceExplained": 0.0041711175
  },
  "dropped_31": {
    "CumulativeVarianceExplained": 0.4118722784,
    "Mask": "Edge",
    "Method": "EdgeRegressor",
    "Retained": false,
    "SingularValue": 107.994894945,
    "VarianceExplained": 0.0041623474
  },
  "dropped_32": {
    "CumulativeVarianceExplained": 0.4160125176,
    "Mask": "Edge",
    "Method": "EdgeRegressor",
    "Retained": false,
    "SingularValue": 107.7077071912,
    "VarianceExplained": 0.0041402392
  },
  "dropped_33": {
    "CumulativeVarianceExplained": 0.4201469792,
    "Mask": "Edge",
    "Method": "EdgeRegressor",
    "Retained": false,
    "SingularValue": 107.6325293536,
    "VarianceExplained": 0.0041344616
  },
  "dropped_34": {
    "CumulativeVarianceExplained": 0.4242711005,
    "Mask": "Edge",
    "Method": "EdgeRegressor",
    "Retained": false,
    "SingularValue": 107.4978505351,
    "VarianceExplained": 0.0041241213
  },
  "dropped_35": {
    "CumulativeVarianceExplained": 0.4283767107,
    "Mask": "Edge",
    "Method": "EdgeRegressor",
    "Retained": false,
    "SingularValue": 107.2563274314,
    "VarianceExplained": 0.0041056102
  },
  "dropped_36": {
    "CumulativeVarianceExplained": 0.4324601217,
    "Mask": "Edge",
    "Method": "EdgeRegressor",
    "Retained": false,
    "SingularValue": 106.9659652541,
    "VarianceExplained": 0.004083411
  },
  "dropped_37": {
    "CumulativeVarianceExplained": 0.4365356293,
    "Mask": "Edge",
    "Method": "EdgeRegressor",
    "Retained": false,
    "SingularValue": 106.86239788,
    "VarianceExplained": 0.0040755075
  },
  "dropped_38": {
    "CumulativeVarianceExplained": 0.4406009259,
    "Mask": "Edge",
    "Method": "EdgeRegressor",
    "Retained": false,
    "SingularValue": 106.7284466519,
    "VarianceExplained": 0.0040652967
  },
  "dropped_39": {
    "CumulativeVarianceExplained": 0.4446558728,
    "Mask": "Edge",
    "Method": "EdgeRegressor",
    "Retained": false,
    "SingularValue": 106.592500516,
    "VarianceExplained": 0.0040549469
  },
  "dropped_4": {
    "CumulativeVarianceExplained": 0.2930497727,
    "Mask": "Edge",
    "Method": "EdgeRegressor",
    "Retained": false,
    "SingularValue": 115.8865854018,
    "VarianceExplained": 0.0047928982
  },
  "dropped_40": {
    "CumulativeVarianceExplained": 0.4487017915,
    "Mask": "Edge",
    "Method": "EdgeRegressor",
    "Retained": false,
    "SingularValue": 106.47377251,
    "VarianceExplained": 0.0040459187
  },
  "dropped_41": {
    "CumulativeVarianceExplained": 0.4527306429,
    "Mask": "Edge",
    "Method": "EdgeRegressor",
    "Retained": false,
    "SingularValue": 106.2489604445,
    "VarianceExplained": 0.0040288514
  },
  "dropped_42": {
    "CumulativeVarianceExplained": 0.4567518189,
    "Mask": "Edge",
    "Method": "EdgeRegressor",
    "Retained": false,
    "SingularValue": 106.1477045567,
    "VarianceExplained": 0.004021176
  },
  "dropped_43": {
    "CumulativeVarianceExplained": 0.460764471,
    "Mask": "Edge",
    "Method": "EdgeRegressor",
    "Retained": false,
    "SingularValue": 106.0351405141,
    "VarianceExplained": 0.004012652
  },
  "dropped_44": {
    "CumulativeVarianceExplained": 0.4647704108,
    "Mask": "Edge",
    "Method": "EdgeRegressor",
    "Retained": false,
    "SingularValue": 105.9464169828,
    "VarianceExplained": 0.0040059398
  },
  "dropped_45": {
    "CumulativeVarianceExplained": 0.4687649102,
    "Mask": "Edge",
    "Method": "EdgeRegressor",
    "Retained": false,
    "SingularValue": 105.7950249802,
    "VarianceExplained": 0.0039944994
  },
  "dropped_46": {
    "CumulativeVarianceExplained": 0.4727454415,
    "Mask": "Edge",
    "Method": "EdgeRegressor",
    "Retained": false,
    "SingularValue": 105.6098900076,
    "VarianceExplained": 0.0039805314
  },
  "dropped_47": {
    "CumulativeVarianceExplained": 0.4767205854,
    "Mask": "Edge",
    "Method": "EdgeRegressor",
    "Retained": false,
    "SingularValue": 105.5383964715,
    "VarianceExplained": 0.0039751439
  },
  "dropped_48": {
    "CumulativeVarianceExplained": 0.480687498,
    "Mask": "Edge",
    "Method": "EdgeRegressor",
    "Retained": false,
    "SingularValue": 105.4290720407,
    "VarianceExplained": 0.0039669126
  },
  "dropped_49": {
    "CumulativeVarianceExplained": 0.4846462184,
    "Mask": "Edge",
    "Method": "EdgeRegressor",
    "Retained": false,
    "SingularValue": 105.3201523822,
    "VarianceExplained": 0.0039587204
  },
  "dropped_5": {
    "CumulativeVarianceExplained": 0.2977932179,
    "Mask": "Edge",
    "Method": "EdgeRegressor",
    "Retained": false,
    "SingularValue": 115.2871792183,
    "VarianceExplained": 0.0047434453
  },
  "dropped_50": {
    "CumulativeVarianceExplained": 0.4885890122,
    "Mask": "Edge",
    "Method": "EdgeRegressor",
    "Retained": false,
    "SingularValue": 105.1080785802,
    "VarianceExplained": 0.0039427938
  },
  "dropped_51": {
    "CumulativeVarianceExplained": 0.4925239688,
    "Mask": "Edge",
    "Method": "EdgeRegressor",
    "Retained": false,
    "SingularValue": 105.0035643364,
    "VarianceExplained": 0.0039349566
  },
  "dropped_52": {
    "CumulativeVarianceExplained": 0.4964464402,
    "Mask": "Edge",
    "Method": "EdgeRegressor",
    "Retained": false,
    "SingularValue": 104.8368486465,
    "VarianceExplained": 0.0039224714
  },
  "dropped_53": {
    "CumulativeVarianceExplained": 0.5003645027,
    "Mask": "Edge",
    "Method": "EdgeRegressor",
    "Retained": false,
    "SingularValue": 104.7779133652,
    "VarianceExplained": 0.0039180625
  },
  "dropped_54": {
    "CumulativeVarianceExplained": 0.5042607696,
    "Mask": "Edge",
    "Method": "EdgeRegressor",
    "Retained": false,
    "SingularValue": 104.4860747345,
    "VarianceExplained": 0.0038962669
  },
  "dropped_55": {
    "CumulativeVarianceExplained": 0.5081403817,
    "Mask": "Edge",
    "Method": "EdgeRegressor",
    "Retained": false,
    "SingularValue": 104.2625194714,
    "VarianceExplained": 0.0038796121
  },
  "dropped_56": {
    "CumulativeVarianceExplained": 0.5120135499,
    "Mask": "Edge",
    "Method": "EdgeRegressor",
    "Retained": false,
    "SingularValue": 104.1758969367,
    "VarianceExplained": 0.0038731683
  },
  "dropped_57": {
    "CumulativeVarianceExplained": 0.5158786458,
    "Mask": "Edge",
    "Method": "EdgeRegressor",
    "Retained": false,
    "SingularValue": 104.0672788503,
    "VarianceExplained": 0.0038650958
  },
  "dropped_58": {
    "CumulativeVarianceExplained": 0.5197334436,
    "Mask": "Edge",
    "Method": "EdgeRegressor",
    "Retained": false,
    "SingularValue": 103.9285503873,
    "VarianceExplained": 0.0038547979
  },
  "dropped_59": {
    "CumulativeVarianceExplained": 0.5235758722,
    "Mask": "Edge",
    "Method": "EdgeRegressor",
    "Retained": false,
    "SingularValue": 103.7616733745,
    "VarianceExplained": 0.0038424286
  },
  "dropped_6": {
    "CumulativeVarianceExplained": 0.3025224565,
    "Mask": "Edge",
    "Method": "EdgeRegressor",
    "Retained": false,
    "SingularValue": 115.1144061603,
    "VarianceExplained": 0.0047292386
  },
  "dropped_60": {
    "CumulativeVarianceExplained": 0.5274082623,
    "Mask": "Edge",
    "Method": "EdgeRegressor",
    "Retained": false,
    "SingularValue": 103.626044767,
    "VarianceExplained": 0.0038323901
  },
  "dropped_61": {
    "CumulativeVarianceExplained": 0.5312305262,
    "Mask": "Edge",
    "Method": "EdgeRegressor",
    "Retained": false,
    "SingularValue": 103.4890492937,
    "VarianceExplained": 0.0038222639
  },
  "dropped_62": {
    "CumulativeVarianceExplained": 0.5350364252,
    "Mask": "Edge",
    "Method": "EdgeRegressor",
    "Retained": false,
    "SingularValue": 103.2672701444,
    "VarianceExplained": 0.003805899
  },
  "dropped_63": {
    "CumulativeVarianceExplained": 0.5388321915,
    "Mask": "Edge",
    "Method": "EdgeRegressor",
    "Retained": false,
    "SingularValue": 103.1297106675,
    "VarianceExplained": 0.0037957663
  },
  "dropped_64": {
    "CumulativeVarianceExplained": 0.5426211888,
    "Mask": "Edge",
    "Method": "EdgeRegressor",
    "Retained": false,
    "SingularValue": 103.0377127933,
    "VarianceExplained": 0.0037889972
  },
  "dropped_65": {
    "CumulativeVarianceExplained": 0.546403067,
    "Mask": "Edge",
    "Method": "EdgeRegressor",
    "Retained": false,
    "SingularValue": 102.9408696726,
    "VarianceExplained": 0.0037818782
  },
  "dropped_66": {
    "CumulativeVarianceExplained": 0.5501765454,
    "Mask": "Edge",
    "Method": "EdgeRegressor",
    "Retained": false,
    "SingularValue": 102.8264875643,
    "VarianceExplained": 0.0037734784
  },
  "dropped_67": {
    "CumulativeVarianceExplained": 0.5539308105,
    "Mask": "Edge",
    "Method": "EdgeRegressor",
    "Retained": false,
    "SingularValue": 102.5643736727,
    "VarianceExplained": 0.0037542651
  },
  "dropped_68": {
    "CumulativeVarianceExplained": 0.5576815377,
    "Mask": "Edge",
    "Method": "EdgeRegressor",
    "Retained": false,
    "SingularValue": 102.5160360397,
    "VarianceExplained": 0.0037507272
  },
  "dropped_69": {
    "CumulativeVarianceExplained": 0.561418581,
    "Mask": "Edge",
    "Method": "EdgeRegressor",
    "Retained": false,
    "SingularValue": 102.3288591583,
    "VarianceExplained": 0.0037370433
  },
  "dropped_7": {
    "CumulativeVarianceExplained": 0.3071939472,
    "Mask": "Edge",
    "Method": "EdgeRegressor",
    "Retained": false,
    "SingularValue": 114.4094262176,
    "VarianceExplained": 0.0046714907
  },
  "dropped_70": {
    "CumulativeVarianceExplained": 0.5651495545,
    "Mask": "Edge",
    "Method": "EdgeRegressor",
    "Retained": false,
    "SingularValue": 102.2457219283,
    "VarianceExplained": 0.0037309735
  },
  "dropped_71": {
    "CumulativeVarianceExplained": 0.568879569,
    "Mask": "Edge",
    "Method": "EdgeRegressor",
    "Retained": false,
    "SingularValue": 102.2325817638,
    "VarianceExplained": 0.0037300146
  },
  "dropped_72": {
    "CumulativeVarianceExplained": 0.5725897127,
    "Mask": "Edge",
    "Method": "EdgeRegressor",
    "Retained": false,
    "SingularValue": 101.9599073775,
    "VarianceExplained": 0.0037101437
  },
  "dropped_73": {
    "CumulativeVarianceExplained": 0.5762905621,
    "Mask": "Edge",
    "Method": "EdgeRegressor",
    "Retained": false,
    "SingularValue": 101.8321161606,
    "VarianceExplained": 0.0037008494
  },
  "dropped_74": {
    "CumulativeVarianceExplained": 0.5799826306,
    "Mask": "Edge",
    "Method": "EdgeRegressor",
    "Retained": false,
    "SingularValue": 101.7112386986,
    "VarianceExplained": 0.0036920686
  },
  "dropped_75": {
    "CumulativeVarianceExplained": 0.583668741,
    "Mask": "Edge",
    "Method": "EdgeRegressor",
    "Retained": false,
    "SingularValue": 101.6291362563,
    "VarianceExplained": 0.0036861104
  },
  "dropped_76": {
    "CumulativeVarianceExplained": 0.5873454196,
    "Mask": "Edge",
    "Method": "EdgeRegressor",
    "Retained": false,
    "SingularValue": 101.4990310803,
    "VarianceExplained": 0.0036766786
  },
  "dropped_77": {
    "CumulativeVarianceExplained": 0.5910110522,
    "Mask": "Edge",
    "Method": "EdgeRegressor",
    "Retained": false,
    "SingularValue": 101.3464476382,
    "VarianceExplained": 0.0036656326
  },
  "dropped_78": {
    "CumulativeVarianceExplained": 0.5946626696,
    "Mask": "Edge",
    "Method": "EdgeRegressor",
    "Retained": false,
    "SingularValue": 101.1525193003,
    "VarianceExplained": 0.0036516175
  },
  "dropped_79": {
    "CumulativeVarianceExplained": 0.5983066835,
    "Mask": "Edge",
    "Method": "EdgeRegressor",
    "Retained": false,
    "SingularValue": 101.0471510639,
    "VarianceExplained": 0.0036440138
  },
  "dropped_8": {
    "CumulativeVarianceExplained": 0.3118047524,
    "Mask": "Edge",
    "Method": "EdgeRegressor",
    "Retained": false,
    "SingularValue": 113.6638737771,
    "VarianceExplained": 0.0046108052
  },
  "dropped_80": {
    "CumulativeVarianceExplained": 0.6019468642,
    "Mask": "Edge",
    "Method": "EdgeRegressor",
    "Retained": false,
    "SingularValue": 100.9939924349,
    "VarianceExplained": 0.0036401808
  },
  "dropped_81": {
    "CumulativeVarianceExplained": 0.6055767106,
    "Mask": "Edge",
    "Method": "EdgeRegressor",
    "Retained": false,
    "SingularValue": 100.8505305441,
    "VarianceExplained": 0.0036298464
  },
  "dropped_82": {
    "CumulativeVarianceExplained": 0.6092027236,
    "Mask": "Edge",
    "Method": "EdgeRegressor",
    "Retained": false,
    "SingularValue": 100.7972638421,
    "VarianceExplained": 0.003626013
  },
  "dropped_83": {
    "CumulativeVarianceExplained": 0.6128189381,
    "Mask": "Edge",
    "Method": "EdgeRegressor",
    "Retained": false,
    "SingularValue": 100.6609803684,
    "VarianceExplained": 0.0036162145
  },
  "dropped_84": {
    "CumulativeVarianceExplained": 0.6164312186,
    "Mask": "Edge",
    "Method": "EdgeRegressor",
    "Retained": false,
    "SingularValue": 100.6062132068,
    "VarianceExplained": 0.0036122806
  },
  "dropped_85": {
    "CumulativeVarianceExplained": 0.6200246862,
    "Mask": "Edge",
    "Method": "EdgeRegressor",
    "Retained": false,
    "SingularValue": 100.3438892961,
    "VarianceExplained": 0.0035934676
  },
  "dropped_86": {
    "CumulativeVarianceExplained": 0.6236077346,
    "Mask": "Edge",
    "Method": "EdgeRegressor",
    "Retained": false,
    "SingularValue": 100.198311095,
    "VarianceExplained": 0.0035830484
  },
  "dropped_87": {
    "CumulativeVarianceExplained": 0.6271835301,
    "Mask": "Edge",
    "Method": "EdgeRegressor",
    "Retained": false,
    "SingularValue": 100.0968487053,
    "VarianceExplained": 0.0035757955
  },
  "dropped_88": {
    "CumulativeVarianceExplained": 0.6307546528,
    "Mask": "Edge",
    "Method": "EdgeRegressor",
    "Retained": false,
    "SingularValue": 100.0314242168,
    "VarianceExplained": 0.0035711227
  },
  "dropped_89": {
    "CumulativeVarianceExplained": 0.6343087932,
    "Mask": "Edge",
    "Method": "EdgeRegressor",
    "Retained": false,
    "SingularValue": 99.7932923872,
    "VarianceExplained": 0.0035541403
  },
  "dropped_9": {
    "CumulativeVarianceExplained": 0.3163846778,
    "Mask": "Edge",
    "Method": "EdgeRegressor",
    "Retained": false,
    "SingularValue": 113.282614933,
    "VarianceExplained": 0.0045799254
  },
  "dropped_90": {
    "CumulativeVarianceExplained": 0.6378523449,
    "Mask": "Edge",
    "Method": "EdgeRegressor",
    "Retained": false,
    "SingularValue": 99.6445275027,
    "VarianceExplained": 0.0035435517
  },
  "dropped_91": {
    "CumulativeVarianceExplained": 0.6413917841,
    "Mask": "Edge",
    "Method": "EdgeRegressor",
    "Retained": false,
    "SingularValue": 99.5866890802,
    "VarianceExplained": 0.0035394392
  },
  "dropped_92": {
    "CumulativeVarianceExplained": 0.6449206599,
    "Mask": "Edge",
    "Method": "EdgeRegressor",
    "Retained": false,
    "SingularValue": 99.4379708624,
    "VarianceExplained": 0.0035288758
  },
  "dropped_93": {
    "CumulativeVarianceExplained": 0.6484464564,
    "Mask": "Edge",
    "Method": "EdgeRegressor",
    "Retained": false,
    "SingularValue": 99.394576086,
    "VarianceExplained": 0.0035257965
  },
  "dropped_94": {
    "CumulativeVarianceExplained": 0.6519637905,
    "Mask": "Edge",
    "Method": "EdgeRegressor",
    "Retained": false,
    "SingularValue": 99.2752247127,
    "VarianceExplained": 0.0035173341
  },
  "dropped_95": {
    "CumulativeVarianceExplained": 0.6554771344,
    "Mask": "Edge",
    "Method": "EdgeRegressor",
    "Retained": false,
    "SingularValue": 99.2188977335,
    "VarianceExplained": 0.0035133439
  },
  "dropped_96": {
    "CumulativeVarianceExplained": 0.6589810535,
    "Mask": "Edge",
    "Method": "EdgeRegressor",
    "Retained": false,
    "SingularValue": 99.0857263409,
    "VarianceExplained": 0.003503919
  },
  "dropped_97": {
    "CumulativeVarianceExplained": 0.6624755908,
    "Mask": "Edge",
    "Method": "EdgeRegressor",
    "Retained": false,
    "SingularValue": 98.952986769,
    "VarianceExplained": 0.0034945373
  },
  "dropped_98": {
    "CumulativeVarianceExplained": 0.6659636806,
    "Mask": "Edge",
    "Method": "EdgeRegressor",
    "Retained": false,
    "SingularValue": 98.8616591393,
    "VarianceExplained": 0.0034880898
  },
  "dropped_99": {
    "CumulativeVarianceExplained": 0.669443395,
    "Mask": "Edge",
    "Method": "EdgeRegressor",
    "Retained": false,
    "SingularValue": 98.7428975189,
    "VarianceExplained": 0.0034797144
  },
  "edge_comp_00": {
    "CumulativeVarianceExplained": 0.0391080058,
    "Mask": "Edge",
    "Method": "EdgeRegressor",
    "Retained": true,
    "SingularValue": 331.0296548296,
    "VarianceExplained": 0.0391080058
  },
  "edge_comp_01": {
    "CumulativeVarianceExplained": 0.0723506316,
    "Mask": "Edge",
    "Method": "EdgeRegressor",
    "Retained": true,
    "SingularValue": 305.1980298695,
    "VarianceExplained": 0.0332426258
  },
  "edge_comp_02": {
    "CumulativeVarianceExplained": 0.0992897105,
    "Mask": "Edge",
    "Method": "EdgeRegressor",
    "Retained": true,
    "SingularValue": 274.7422410339,
    "VarianceExplained": 0.0269390789
  },
  "edge_comp_03": {
    "CumulativeVarianceExplained": 0.1194544952,
    "Mask": "Edge",
    "Method": "EdgeRegressor",
    "Retained": true,
    "SingularValue": 237.7009188875,
    "VarianceExplained": 0.0201647847
  },
  "edge_comp_04": {
    "CumulativeVarianceExplained": 0.1324882147,
    "Mask": "Edge",
    "Method": "EdgeRegressor",
    "Retained": true,
    "SingularValue": 191.1033275354,
    "VarianceExplained": 0.0130337194
  },
  "edge_comp_05": {
    "CumulativeVarianceExplained": 0.1446286623,
    "Mask": "Edge",
    "Method": "EdgeRegressor",
    "Retained": true,
    "SingularValue": 184.4384294417,
    "VarianceExplained": 0.0121404476
  },
  "edge_comp_06": {
    "CumulativeVarianceExplained": 0.1559662781,
    "Mask": "Edge",
    "Method": "EdgeRegressor",
    "Retained": true,
    "SingularValue": 178.2357978437,
    "VarianceExplained": 0.0113376159
  },
  "edge_comp_07": {
    "CumulativeVarianceExplained": 0.1659011682,
    "Mask": "Edge",
    "Method": "EdgeRegressor",
    "Retained": true,
    "SingularValue": 166.8459231291,
    "VarianceExplained": 0.0099348901
  },
  "edge_comp_08": {
    "CumulativeVarianceExplained": 0.1753527752,
    "Mask": "Edge",
    "Method": "EdgeRegressor",
    "Retained": true,
    "SingularValue": 162.7372199355,
    "VarianceExplained": 0.009451607
  },
  "edge_comp_09": {
    "CumulativeVarianceExplained": 0.1840787353,
    "Mask": "Edge",
    "Method": "EdgeRegressor",
    "Retained": true,
    "SingularValue": 156.3654062957,
    "VarianceExplained": 0.0087259601
  },
  "edge_comp_10": {
    "CumulativeVarianceExplained": 0.1919429191,
    "Mask": "Edge",
    "Method": "EdgeRegressor",
    "Retained": true,
    "SingularValue": 148.4433995489,
    "VarianceExplained": 0.0078641838
  },
  "edge_comp_11": {
    "CumulativeVarianceExplained": 0.19965345,
    "Mask": "Edge",
    "Method": "EdgeRegressor",
    "Retained": true,
    "SingularValue": 146.9860797475,
    "VarianceExplained": 0.0077105309
  },
  "edge_comp_12": {
    "CumulativeVarianceExplained": 0.2069658167,
    "Mask": "Edge",
    "Method": "EdgeRegressor",
    "Retained": true,
    "SingularValue": 143.1406698947,
    "VarianceExplained": 0.0073123667
  },
  "edge_comp_13": {
    "CumulativeVarianceExplained": 0.2135073931,
    "Mask": "Edge",
    "Method": "EdgeRegressor",
    "Retained": true,
    "SingularValue": 135.3864731003,
    "VarianceExplained": 0.0065415764
  },
  "edge_comp_14": {
    "CumulativeVarianceExplained": 0.2196266156,
    "Mask": "Edge",
    "Method": "EdgeRegressor",
    "Retained": true,
    "SingularValue": 130.9429700974,
    "VarianceExplained": 0.0061192225
  },
  "edge_comp_15": {
    "CumulativeVarianceExplained": 0.2256740867,
    "Mask": "Edge",
    "Method": "EdgeRegressor",
    "Retained": true,
    "SingularValue": 130.1730162642,
    "VarianceExplained": 0.0060474712
  },
  "edge_comp_16": {
    "CumulativeVarianceExplained": 0.231420867,
    "Mask": "Edge",
    "Method": "EdgeRegressor",
    "Retained": true,
    "SingularValue": 126.8955415059,
    "VarianceExplained": 0.0057467803
  },
  "edge_comp_17": {
    "CumulativeVarianceExplained": 0.2370598292,
    "Mask": "Edge",
    "Method": "EdgeRegressor",
    "Retained": true,
    "SingularValue": 125.6995300007,
    "VarianceExplained": 0.0056389621
  },
  "edge_comp_18": {
    "CumulativeVarianceExplained": 0.2425047865,
    "Mask": "Edge",
    "Method": "EdgeRegressor",
    "Retained": true,
    "SingularValue": 123.5182999426,
    "VarianceExplained": 0.0054449573
  },
  "edge_comp_19": {
    "CumulativeVarianceExplained": 0.2479149057,
    "Mask": "Edge",
    "Method": "EdgeRegressor",
    "Retained": true,
    "SingularValue": 123.1225163388,
    "VarianceExplained": 0.0054101192
  },
  "edge_comp_20": {
    "CumulativeVarianceExplained": 0.2531785129,
    "Mask": "Edge",
    "Method": "EdgeRegressor",
    "Retained": true,
    "SingularValue": 121.4439265076,
    "VarianceExplained": 0.0052636072
  },
  "edge_comp_21": {
    "CumulativeVarianceExplained": 0.2583856107,
    "Mask": "Edge",
    "Method": "EdgeRegressor",
    "Retained": true,
    "SingularValue": 120.7902656318,
    "VarianceExplained": 0.0052070979
  },
  "edge_comp_22": {
    "CumulativeVarianceExplained": 0.2635413293,
    "Mask": "Edge",
    "Method": "EdgeRegressor",
    "Retained": true,
    "SingularValue": 120.1928589545,
    "VarianceExplained": 0.0051557185
  },
  "edge_comp_23": {
    "CumulativeVarianceExplained": 0.2685914065,
    "Mask": "Edge",
    "Method": "EdgeRegressor",
    "Retained": true,
    "SingularValue": 118.9551022841,
    "VarianceExplained": 0.0050500772
  },
  "framewise_displacement": {
    "Units": "mm"
  },
  "rot_x": {
    "Description": "Rotation about left-right axis. Also known as \"pitch\".",
    "Units": "rad"
  },
  "rot_y": {
    "Description": "Rotation about anterior-posterior axis. Also known as \"roll\".",
    "Units": "rad"
  },
  "rot_z": {
    "Description": "Rotation about superior-inferior axis. Also known as \"yaw\".",
    "Units": "rad"
  },
  "t_comp_cor_00": {
    "CumulativeVarianceExplained": 0.1341287272,
    "Method": "tCompCor",
    "Retained": true,
    "SingularValue": 161.9740072926,
    "VarianceExplained": 0.1341287272
  },
  "t_comp_cor_01": {
    "CumulativeVarianceExplained": 0.2518509797,
    "Method": "tCompCor",
    "Retained": true,
    "SingularValue": 151.7447613589,
    "VarianceExplained": 0.1177222526
  },
  "t_comp_cor_02": {
    "CumulativeVarianceExplained": 0.3499407572,
    "Method": "tCompCor",
    "Retained": true,
    "SingularValue": 138.5148384572,
    "VarianceExplained": 0.0980897775
  },
  "t_comp_cor_03": {
    "CumulativeVarianceExplained": 0.4363294033,
    "Method": "tCompCor",
    "Retained": true,
    "SingularValue": 129.9908426866,
    "VarianceExplained": 0.0863886461
  },
  "t_comp_cor_04": {
    "CumulativeVarianceExplained": 0.4865277406,
    "Method": "tCompCor",
    "Retained": true,
    "SingularValue": 99.089831822,
    "VarianceExplained": 0.0501983373
  },
  "t_comp_cor_05": {
    "CumulativeVarianceExplained": 0.5286552214,
    "Method": "tCompCor",
    "Retained": true,
    "SingularValue": 90.775190659,
    "VarianceExplained": 0.0421274808
  },
  "trans_x": {
    "Description": "Translation along left-right axis.",
    "Units": "mm"
  },
  "trans_y": {
    "Description": "Translation along anterior-posterior axis.",
    "Units": "mm"
  },
  "trans_z": {
    "Description": "Translation along superior-inferior axis.",
    "Units": "mm"
  },
  "w_comp_cor_00": {
    "CumulativeVarianceExplained": 0.0114832482,
    "Mask": "WM",
    "Method": "aCompCor",
    "Retained": true,
    "SingularValue": 61.3344283731,
    "VarianceExplained": 0.0114832482
  },
  "w_comp_cor_01": {
    "CumulativeVarianceExplained": 0.0220423095,
    "Mask": "WM",
    "Method": "aCompCor",
    "Retained": true,
    "SingularValue": 58.814526222,
    "VarianceExplained": 0.0105590613
  },
  "w_comp_cor_02": {
    "CumulativeVarianceExplained": 0.0318390421,
    "Mask": "WM",
    "Method": "aCompCor",
    "Retained": true,
    "SingularValue": 56.6516513038,
    "VarianceExplained": 0.0097967326
  },
  "w_comp_cor_03": {
    "CumulativeVarianceExplained": 0.0412938716,
    "Mask": "WM",
    "Method": "aCompCor",
    "Retained": true,
    "SingularValue": 55.6543092163,
    "VarianceExplained": 0.0094548295
  },
  "w_comp_cor_04": {
    "CumulativeVarianceExplained": 0.0500059843,
    "Mask": "WM",
    "Method": "aCompCor",
    "Retained": true,
    "SingularValue": 53.4236664291,
    "VarianceExplained": 0.0087121127
  },
  "w_comp_cor_05": {
    "CumulativeVarianceExplained": 0.0585555149,
    "Mask": "WM",
    "Method": "aCompCor",
    "Retained": true,
    "SingularValue": 52.9228325789,
    "VarianceExplained": 0.0085495305
  },
  "w_comp_cor_06": {
    "CumulativeVarianceExplained": 0.0668942798,
    "Mask": "WM",
    "Method": "aCompCor",
    "Retained": true,
    "SingularValue": 52.266427044,
    "VarianceExplained": 0.0083387649
  },
  "w_comp_cor_07": {
    "CumulativeVarianceExplained": 0.0751271363,
    "Mask": "WM",
    "Method": "aCompCor",
    "Retained": true,
    "SingularValue": 51.9334555017,
    "VarianceExplained": 0.0082328565
  },
  "w_comp_cor_08": {
    "CumulativeVarianceExplained": 0.0833274527,
    "Mask": "WM",
    "Method": "aCompCor",
    "Retained": true,
    "SingularValue": 51.830720962,
    "VarianceExplained": 0.0082003163
  },
  "w_comp_cor_09": {
    "CumulativeVarianceExplained": 0.0913720335,
    "Mask": "WM",
    "Method": "aCompCor",
    "Retained": true,
    "SingularValue": 51.3361925919,
    "VarianceExplained": 0.0080445808
  },
  "w_comp_cor_10": {
    "CumulativeVarianceExplained": 0.0993384388,
    "Mask": "WM",
    "Method": "aCompCor",
    "Retained": true,
    "SingularValue": 51.0861466823,
    "VarianceExplained": 0.0079664053
  },
  "w_comp_cor_11": {
    "CumulativeVarianceExplained": 0.1072295383,
    "Mask": "WM",
    "Method": "aCompCor",
    "Retained": true,
    "SingularValue": 50.8441164541,
    "VarianceExplained": 0.0078910994
  },
  "w_comp_cor_12": {
    "CumulativeVarianceExplained": 0.1149424294,
    "Mask": "WM",
    "Method": "aCompCor",
    "Retained": true,
    "SingularValue": 50.2667199817,
    "VarianceExplained": 0.0077128911
  },
  "w_comp_cor_13": {
    "CumulativeVarianceExplained": 0.1226087421,
    "Mask": "WM",
    "Method": "aCompCor",
    "Retained": true,
    "SingularValue": 50.1147087124,
    "VarianceExplained": 0.0076663127
  },
  "w_comp_cor_14": {
    "CumulativeVarianceExplained": 0.1301908612,
    "Mask": "WM",
    "Method": "aCompCor",
    "Retained": true,
    "SingularValue": 49.8387623571,
    "VarianceExplained": 0.0075821191
  },
  "w_comp_cor_15": {
    "CumulativeVarianceExplained": 0.1377155922,
    "Mask": "WM",
    "Method": "aCompCor",
    "Retained": true,
    "SingularValue": 49.6497921996,
    "VarianceExplained": 0.007524731
  },
  "w_comp_cor_16": {
    "CumulativeVarianceExplained": 0.1451404014,
    "Mask": "WM",
    "Method": "aCompCor",
    "Retained": true,
    "SingularValue": 49.3190379912,
    "VarianceExplained": 0.0074248092
  },
  "w_comp_cor_17": {
    "CumulativeVarianceExplained": 0.1525270414,
    "Mask": "WM",
    "Method": "aCompCor",
    "Retained": true,
    "SingularValue": 49.1921056995,
    "VarianceExplained": 0.00738664
  },
  "w_comp_cor_18": {
    "CumulativeVarianceExplained": 0.1598624882,
    "Mask": "WM",
    "Method": "aCompCor",
    "Retained": true,
    "SingularValue": 49.0213460538,
    "VarianceExplained": 0.0073354468
  },
  "w_comp_cor_19": {
    "CumulativeVarianceExplained": 0.1671566505,
    "Mask": "WM",
    "Method": "aCompCor",
    "Retained": true,
    "SingularValue": 48.8832034065,
    "VarianceExplained": 0.0072941623
  },
  "w_comp_cor_20": {
    "CumulativeVarianceExplained": 0.1743466652,
    "Mask": "WM",
    "Method": "aCompCor",
    "Retained": true,
    "SingularValue": 48.5329662183,
    "VarianceExplained": 0.0071900147
  },
  "w_comp_cor_21": {
    "CumulativeVarianceExplained": 0.1814759639,
    "Mask": "WM",
    "Method": "aCompCor",
    "Retained": true,
    "SingularValue": 48.3276135765,
    "VarianceExplained": 0.0071292986
  },
  "w_comp_cor_22": {
    "CumulativeVarianceExplained": 0.1886034182,
    "Mask": "WM",
    "Method": "aCompCor",
    "Retained": true,
    "SingularValue": 48.3213621944,
    "VarianceExplained": 0.0071274543
  },
  "w_comp_cor_23": {
    "CumulativeVarianceExplained": 0.1956409933,
    "Mask": "WM",
    "Method": "aCompCor",
    "Retained": true,
    "SingularValue": 48.0157223356,
    "VarianceExplained": 0.0070375751
  },
  "w_comp_cor_24": {
    "CumulativeVarianceExplained": 0.2026464267,
    "Mask": "WM",
    "Method": "aCompCor",
    "Retained": true,
    "SingularValue": 47.905949428,
    "VarianceExplained": 0.0070054334
  },
  "w_comp_cor_25": {
    "CumulativeVarianceExplained": 0.2095584657,
    "Mask": "WM",
    "Method": "aCompCor",
    "Retained": true,
    "SingularValue": 47.5855436831,
    "VarianceExplained": 0.006912039
  },
  "w_comp_cor_26": {
    "CumulativeVarianceExplained": 0.2164452746,
    "Mask": "WM",
    "Method": "aCompCor",
    "Retained": true,
    "SingularValue": 47.4986169167,
    "VarianceExplained": 0.0068868089
  },
  "w_comp_cor_27": {
    "CumulativeVarianceExplained": 0.223282555,
    "Mask": "WM",
    "Method": "aCompCor",
    "Retained": true,
    "SingularValue": 47.3275085249,
    "VarianceExplained": 0.0068372804
  },
  "w_comp_cor_28": {
    "CumulativeVarianceExplained": 0.2300707815,
    "Mask": "WM",
    "Method": "aCompCor",
    "Retained": true,
    "SingularValue": 47.1574276965,
    "VarianceExplained": 0.0067882265
  },
  "w_comp_cor_29": {
    "CumulativeVarianceExplained": 0.2368083697,
    "Mask": "WM",
    "Method": "aCompCor",
    "Retained": true,
    "SingularValue": 46.9812078458,
    "VarianceExplained": 0.0067375882
  },
  "w_comp_cor_30": {
    "CumulativeVarianceExplained": 0.2435183024,
    "Mask": "WM",
    "Method": "aCompCor",
    "Retained": true,
    "SingularValue": 46.8846881147,
    "VarianceExplained": 0.0067099328
  },
  "w_comp_cor_31": {
    "CumulativeVarianceExplained": 0.250225213,
    "Mask": "WM",
    "Method": "aCompCor",
    "Retained": true,
    "SingularValue": 46.8741281978,
    "VarianceExplained": 0.0067069105
  },
  "w_comp_cor_32": {
    "CumulativeVarianceExplained": 0.256877379,
    "Mask": "WM",
    "Method": "aCompCor",
    "Retained": true,
    "SingularValue": 46.6824333048,
    "VarianceExplained": 0.006652166
  },
  "w_comp_cor_33": {
    "CumulativeVarianceExplained": 0.2634587403,
    "Mask": "WM",
    "Method": "aCompCor",
    "Retained": true,
    "SingularValue": 46.433328243,
    "VarianceExplained": 0.0065813613
  },
  "w_comp_cor_34": {
    "CumulativeVarianceExplained": 0.2700266835,
    "Mask": "WM",
    "Method": "aCompCor",
    "Retained": true,
    "SingularValue": 46.3859696848,
    "VarianceExplained": 0.0065679432
  },
  "w_comp_cor_35": {
    "CumulativeVarianceExplained": 0.2765632449,
    "Mask": "WM",
    "Method": "aCompCor",
    "Retained": true,
    "SingularValue": 46.2750205209,
    "VarianceExplained": 0.0065365614
  },
  "w_comp_cor_36": {
    "CumulativeVarianceExplained": 0.2830461631,
    "Mask": "WM",
    "Method": "aCompCor",
    "Retained": true,
    "SingularValue": 46.0847478325,
    "VarianceExplained": 0.0064829181
  },
  "w_comp_cor_37": {
    "CumulativeVarianceExplained": 0.2895115066,
    "Mask": "WM",
    "Method": "aCompCor",
    "Retained": true,
    "SingularValue": 46.0222395466,
    "VarianceExplained": 0.0064653435
  },
  "w_comp_cor_38": {
    "CumulativeVarianceExplained": 0.2959365543,
    "Mask": "WM",
    "Method": "aCompCor",
    "Retained": true,
    "SingularValue": 45.8785968935,
    "VarianceExplained": 0.0064250478
  },
  "w_comp_cor_39": {
    "CumulativeVarianceExplained": 0.3023316615,
    "Mask": "WM",
    "Method": "aCompCor",
    "Retained": true,
    "SingularValue": 45.7715751267,
    "VarianceExplained": 0.0063951071
  },
  "w_comp_cor_40": {
    "CumulativeVarianceExplained": 0.3086701784,
    "Mask": "WM",
    "Method": "aCompCor",
    "Retained": true,
    "SingularValue": 45.5686091599,
    "VarianceExplained": 0.0063385169
  },
  "w_comp_cor_41": {
    "CumulativeVarianceExplained": 0.3149607719,
    "Mask": "WM",
    "Method": "aCompCor",
    "Retained": true,
    "SingularValue": 45.3960179772,
    "VarianceExplained": 0.0062905936
  },
  "w_comp_cor_42": {
    "CumulativeVarianceExplained": 0.3211967076,
    "Mask": "WM",
    "Method": "aCompCor",
    "Retained": true,
    "SingularValue": 45.1983684595,
    "VarianceExplained": 0.0062359356
  },
  "w_comp_cor_43": {
    "CumulativeVarianceExplained": 0.3273823195,
    "Mask": "WM",
    "Method": "aCompCor",
    "Retained": true,
    "SingularValue": 45.0156247841,
    "VarianceExplained": 0.0061856119
  },
  "w_comp_cor_44": {
    "CumulativeVarianceExplained": 0.3334914535,
    "Mask": "WM",
    "Method": "aCompCor",
    "Retained": true,
    "SingularValue": 44.7364761385,
    "VarianceExplained": 0.006109134
  },
  "w_comp_cor_45": {
    "CumulativeVarianceExplained": 0.3395574303,
    "Mask": "WM",
    "Method": "aCompCor",
    "Retained": true,
    "SingularValue": 44.5781784383,
    "VarianceExplained": 0.0060659768
  },
  "w_comp_cor_46": {
    "CumulativeVarianceExplained": 0.3455974946,
    "Mask": "WM",
    "Method": "aCompCor",
    "Retained": true,
    "SingularValue": 44.4828627497,
    "VarianceExplained": 0.0060400643
  },
  "w_comp_cor_47": {
    "CumulativeVarianceExplained": 0.3516025961,
    "Mask": "WM",
    "Method": "aCompCor",
    "Retained": true,
    "SingularValue": 44.3539314573,
    "VarianceExplained": 0.0060051015
  },
  "w_comp_cor_48": {
    "CumulativeVarianceExplained": 0.357582604,
    "Mask": "WM",
    "Method": "aCompCor",
    "Retained": true,
    "SingularValue": 44.2611636509,
    "VarianceExplained": 0.005980008
  },
  "w_comp_cor_49": {
    "CumulativeVarianceExplained": 0.3635067535,
    "Mask": "WM",
    "Method": "aCompCor",
    "Retained": true,
    "SingularValue": 44.0539595904,
    "VarianceExplained": 0.0059241494
  },
  "w_comp_cor_50": {
    "CumulativeVarianceExplained": 0.369411223,
    "Mask": "WM",
    "Method": "aCompCor",
    "Retained": true,
    "SingularValue": 43.9807254861,
    "VarianceExplained": 0.0059044695
  },
  "w_comp_cor_51": {
    "CumulativeVarianceExplained": 0.3752880776,
    "Mask": "WM",
    "Method": "aCompCor",
    "Retained": true,
    "SingularValue": 43.8777571851,
    "VarianceExplained": 0.0058768546
  },
  "w_comp_cor_52": {
    "CumulativeVarianceExplained": 0.3811485277,
    "Mask": "WM",
    "Method": "aCompCor",
    "Retained": true,
    "SingularValue": 43.8164747563,
    "VarianceExplained": 0.0058604501
  },
  "w_comp_cor_53": {
    "CumulativeVarianceExplained": 0.3869692667,
    "Mask": "WM",
    "Method": "aCompCor",
    "Retained": true,
    "SingularValue": 43.6677695462,
    "VarianceExplained": 0.005820739
  },
  "w_comp_cor_54": {
    "CumulativeVarianceExplained": 0.3927619823,
    "Mask": "WM",
    "Method": "aCompCor",
    "Retained": true,
    "SingularValue": 43.56252555,
    "VarianceExplained": 0.0057927156
  },
  "w_comp_cor_55": {
    "CumulativeVarianceExplained": 0.3984885544,
    "Mask": "WM",
    "Method": "aCompCor",
    "Retained": true,
    "SingularValue": 43.3131043796,
    "VarianceExplained": 0.0057265721
  },
  "w_comp_cor_56": {
    "CumulativeVarianceExplained": 0.4041777365,
    "Mask": "WM",
    "Method": "aCompCor",
    "Retained": true,
    "SingularValue": 43.1714724852,
    "VarianceExplained": 0.005689182
  },
  "w_comp_cor_57": {
    "CumulativeVarianceExplained": 0.4098405776,
    "Mask": "WM",
    "Method": "aCompCor",
    "Retained": true,
    "SingularValue": 43.0714146378,
    "VarianceExplained": 0.0056628411
  },
  "w_comp_cor_58": {
    "CumulativeVarianceExplained": 0.4154459531,
    "Mask": "WM",
    "Method": "aCompCor",
    "Retained": true,
    "SingularValue": 42.8523164462,
    "VarianceExplained": 0.0056053755
  },
  "w_comp_cor_59": {
    "CumulativeVarianceExplained": 0.42101719,
    "Mask": "WM",
    "Method": "aCompCor",
    "Retained": true,
    "SingularValue": 42.7216244512,
    "VarianceExplained": 0.0055712369
  },
  "w_comp_cor_60": {
    "CumulativeVarianceExplained": 0.4265452087,
    "Mask": "WM",
    "Method": "aCompCor",
    "Retained": true,
    "SingularValue": 42.5555981041,
    "VarianceExplained": 0.0055280187
  },
  "w_comp_cor_61": {
    "CumulativeVarianceExplained": 0.432001118,
    "Mask": "WM",
    "Method": "aCompCor",
    "Retained": true,
    "SingularValue": 42.2771317891,
    "VarianceExplained": 0.0054559093
  },
  "w_comp_cor_62": {
    "CumulativeVarianceExplained": 0.4374446906,
    "Mask": "WM",
    "Method": "aCompCor",
    "Retained": true,
    "SingularValue": 42.2293074521,
    "VarianceExplained": 0.0054435727
  },
  "w_comp_cor_63": {
    "CumulativeVarianceExplained": 0.4428799727,
    "Mask": "WM",
    "Method": "aCompCor",
    "Retained": true,
    "SingularValue": 42.1971375386,
    "VarianceExplained": 0.0054352821
  },
  "w_comp_cor_64": {
    "CumulativeVarianceExplained": 0.4482949364,
    "Mask": "WM",
    "Method": "aCompCor",
    "Retained": true,
    "SingularValue": 42.1181919284,
    "VarianceExplained": 0.0054149636
  },
  "w_comp_cor_65": {
    "CumulativeVarianceExplained": 0.4536544572,
    "Mask": "WM",
    "Method": "aCompCor",
    "Retained": true,
    "SingularValue": 41.9020167207,
    "VarianceExplained": 0.0053595208
  },
  "w_comp_cor_66": {
    "CumulativeVarianceExplained": 0.4589890365,
    "Mask": "WM",
    "Method": "aCompCor",
    "Retained": true,
    "SingularValue": 41.8044041438,
    "VarianceExplained": 0.0053345794
  },
  "w_comp_cor_67": {
    "CumulativeVarianceExplained": 0.4643076294,
    "Mask": "WM",
    "Method": "aCompCor",
    "Retained": true,
    "SingularValue": 41.7417180564,
    "VarianceExplained": 0.0053185929
  },
  "w_comp_cor_68": {
    "CumulativeVarianceExplained": 0.4695951526,
    "Mask": "WM",
    "Method": "aCompCor",
    "Retained": true,
    "SingularValue": 41.6196178225,
    "VarianceExplained": 0.0052875232
  },
  "w_comp_cor_69": {
    "CumulativeVarianceExplained": 0.4748704939,
    "Mask": "WM",
    "Method": "aCompCor",
    "Retained": true,
    "SingularValue": 41.5716469044,
    "VarianceExplained": 0.0052753414
  },
  "w_comp_cor_70": {
    "CumulativeVarianceExplained": 0.4801238459,
    "Mask": "WM",
    "Method": "aCompCor",
    "Retained": true,
    "SingularValue": 41.4849142692,
    "VarianceExplained": 0.005253352
  },
  "w_comp_cor_71": {
    "CumulativeVarianceExplained": 0.4853283335,
    "Mask": "WM",
    "Method": "aCompCor",
    "Retained": true,
    "SingularValue": 41.2915262217,
    "VarianceExplained": 0.0052044876
  },
  "w_comp_cor_72": {
    "CumulativeVarianceExplained": 0.4905247521,
    "Mask": "WM",
    "Method": "aCompCor",
    "Retained": true,
    "SingularValue": 41.2595047308,
    "VarianceExplained": 0.0051964186
  },
  "w_comp_cor_73": {
    "CumulativeVarianceExplained": 0.4956651783,
    "Mask": "WM",
    "Method": "aCompCor",
    "Retained": true,
    "SingularValue": 41.0366133425,
    "VarianceExplained": 0.0051404262
  },
  "w_comp_cor_74": {
    "CumulativeVarianceExplained": 0.5007530694,
    "Mask": "WM",
    "Method": "aCompCor",
    "Retained": true,
    "SingularValue": 40.8263776867,
    "VarianceExplained": 0.0050878911
  }
}